Workbook
Name Slicer_Region: #N/A
Name Slicer_Year: #N/A

Sheet territories
A1: TerritoryID | B1: TerritoryDescription | C1: RegionID | D1: Region Description
A2: 1581 | B2: Westboro | C2: 1 | D2: =VLOOKUP(territories[[#This Row],[RegionID]],region[],2,FALSE) -> Eastern
A3: 1730 | B3: Bedford | C3: 1 | D3: =VLOOKUP(territories[[#This Row],[RegionID]],region[],2,FALSE) -> Eastern
A4: 1833 | B4: Georgetow | C4: 1 | D4: =VLOOKUP(territories[[#This Row],[RegionID]],region[],2,FALSE) -> Eastern
A5: 2116 | B5: Boston | C5: 1 | D5: =VLOOKUP(territories[[#This Row],[RegionID]],region[],2,FALSE) -> Eastern
A6: 2139 | B6: Cambridge | C6: 1 | D6: =VLOOKUP(territories[[#This Row],[RegionID]],region[],2,FALSE) -> Eastern
A7: 2184 | B7: Braintree | C7: 1 | D7: =VLOOKUP(territories[[#This Row],[RegionID]],region[],2,FALSE) -> Eastern
A8: 2903 | B8: Providence | C8: 1 | D8: =VLOOKUP(territories[[#This Row],[RegionID]],region[],2,FALSE) -> Eastern
A9: 3049 | B9: Hollis | C9: 3 | D9: =VLOOKUP(territories[[#This Row],[RegionID]],region[],2,FALSE) -> Northern
A10: 3801 | B10: Portsmouth | C10: 3 | D10: =VLOOKUP(territories[[#This Row],[RegionID]],region[],2,FALSE) -> Northern
A11: 6897 | B11: Wilton | C11: 1 | D11: =VLOOKUP(territories[[#This Row],[RegionID]],region[],2,FALSE) -> Eastern
A12: 7960 | B12: Morristown | C12: 1 | D12: =VLOOKUP(territories[[#This Row],[RegionID]],region[],2,FALSE) -> Eastern
A13: 8837 | B13: Edison | C13: 1 | D13: =VLOOKUP(territories[[#This Row],[RegionID]],region[],2,FALSE) -> Eastern
... A54: 98104 | B54: Seattle | C54: 2 | D54: =VLOOKUP(territories[[#This Row],[RegionID]],region[],2,FALSE) -> Westerns

Sheet suppliers
A1: SupplierID | B1: CompanyName | C1: ContactName | D1: ContactTitle | E1: Address | F1: City | G1: Region | H1: PostalCode | I1: Country | J1: Phone | K1: Fax | L1: Supplier Sale | M1: Quantity Supplied
A2: 1 | B2: Exotic Liquids | C2: Charlotte Cooper | D2: Purchasing Manager | E2: 49 Gilbert St. | F2: London | G2: NULL | H2: EC1 4SD | I2: UK | J2: (171) 555-2222 | K2: NULL | L2: =SUMIF(products[SupplierID],suppliers[[#This Row],[SupplierID]],products[[Product Sale ]]) -> 35916.8 | M2: =SUMIF(order_details__2[SupplierID],suppliers[[#This Row],[SupplierID]],order_details__2[Quantity]) -> 2213
A3: 2 | B3: New Orleans Cajun Delights | C3: Shelley Burke | D3: Order Administrator | E3: P.O. Box 78934 | F3: New Orleans | G3: LA | H3: 70117 | I3: USA | J3: (100) 555-4822 | K3: NULL | L3: =SUMIF(products[SupplierID],suppliers[[#This Row],[SupplierID]],products[[Product Sale ]]) -> 33351.95 | M3: =SUMIF(order_details__2[SupplierID],suppliers[[#This Row],[SupplierID]],order_details__2[Quantity]) -> 1735
A4: 3 | B4: Grandma Kelly's Homestead | C4: Regina Murphy | D4: Sales Representative | E4: 707 Oxford Rd. | F4: Ann Arbor | G4: MI | H4: 48104 | I4: USA | J4: (313) 555-5735 | K4: (313) 555-3349 | L4: =SUMIF(products[SupplierID],suppliers[[#This Row],[SupplierID]],products[[Product Sale ]]) -> 43569 | M4: =SUMIF(order_details__2[SupplierID],suppliers[[#This Row],[SupplierID]],order_details__2[Quantity]) -> 1436
A5: 4 | B5: Tokyo Traders | C5: Yoshi Nagase | D5: Marketing Manager | E5: 9-8 Sekimai Musashino-shi | F5: Tokyo | G5: NULL | H5: 100 | I5: Japan | J5: (03) 3555-5011 | K5: NULL | L5: =SUMIF(products[SupplierID],suppliers[[#This Row],[SupplierID]],products[[Product Sale ]]) -> 33533.2 | M5: =SUMIF(order_details__2[SupplierID],suppliers[[#This Row],[SupplierID]],order_details__2[Quantity]) -> 1134
A6: 5 | B6: Cooperativa de Quesos 'Las Cabras' | C6: Antonio del Valle Saavedra | D6: Export Administrator | E6: Calle del Rosal 4 | F6: Oviedo | G6: Asturias | H6: 33007 | I6: Spain | J6: (98) 598 76 54 | K6: NULL | L6: =SUMIF(products[SupplierID],suppliers[[#This Row],[SupplierID]],products[[Product Sale ]]) -> 26768.8 | M6: =SUMIF(order_details__2[SupplierID],suppliers[[#This Row],[SupplierID]],order_details__2[Quantity]) -> 1050
A7: 6 | B7: Mayumi's | C7: Mayumi Ohno | D7: Marketing Representative | E7: 92 Setsuko Chuo-ku | F7: Osaka | G7: NULL | H7: 545 | I7: Japan | J7: (06) 431-7877 | K7: NULL | L7: =SUMIF(products[SupplierID],suppliers[[#This Row],[SupplierID]],products[[Product Sale ]]) -> 15678.3 | M7: =SUMIF(order_details__2[SupplierID],suppliers[[#This Row],[SupplierID]],order_details__2[Quantity]) -> 1417
A8: 7 | B8: Pavlova, Ltd. | C8: Ian Devling | D8: Marketing Manager | E8: 74 Rose St. Moonie Ponds | F8: Melbourne | G8: Victoria | H8: 3058 | I8: Australia | J8: (03) 444-2343 | K8: (03) 444-6588 | L8: =SUMIF(products[SupplierID],suppliers[[#This Row],[SupplierID]],products[[Product Sale ]]) -> 115386.05 | M8: =SUMIF(order_details__2[SupplierID],suppliers[[#This Row],[SupplierID]],order_details__2[Quantity]) -> 3937
A9: 8 | B9: Specialty Biscuits, Ltd. | C9: Peter Wilson | D9: Sales Representative | E9: 29 King's Way | F9: Manchester | G9: NULL | H9: M14 GSD | I9: UK | J9: (161) 555-4448 | K9: NULL | L9: =SUMIF(products[SupplierID],suppliers[[#This Row],[SupplierID]],products[[Product Sale ]]) -> 48793.8 | M9: =SUMIF(order_details__2[SupplierID],suppliers[[#This Row],[SupplierID]],order_details__2[Quantity]) -> 2851
A10: 9 | B10: PB Knckebrd AB | C10: Lars Peterson | D10: Sales Agent | E10: Kaloadagatan 13 | F10: Gteborg | G10: NULL | H10: S-345 67 | I10: Sweden | J10: 031-987 65 43 | K10: 031-987 65 91 | L10: =SUMIF(products[SupplierID],suppliers[[#This Row],[SupplierID]],products[[Product Sale ]]) -> 12072.6 | M10: =SUMIF(order_details__2[SupplierID],suppliers[[#This Row],[SupplierID]],order_details__2[Quantity]) -> 928
A11: 10 | B11: Refrescos Americanas LTDA | C11: Carlos Diaz | D11: Marketing Manager | E11: Av. das Americanas 12.890 | F11: So Paulo | G11: NULL | H11: 5442 | I11: Brazil | J11: (11) 555 4640 | K11: NULL | L11: =SUMIF(products[SupplierID],suppliers[[#This Row],[SupplierID]],products[[Product Sale ]]) -> 4782.6 | M11: =SUMIF(order_details__2[SupplierID],suppliers[[#This Row],[SupplierID]],order_details__2[Quantity]) -> 1125
A12: 11 | B12: Heli Swaren GmbH & Co. KG | C12: Petra Winkler | D12: Sales Manager | E12: Tiergartenstrae 5 | F12: Berlin | G12: NULL | H12: 10785 | I12: Germany | J12: (010) 9984510 | K12: NULL | L12: =SUMIF(products[SupplierID],suppliers[[#This Row],[SupplierID]],products[[Product Sale ]]) -> 40818 | M12: =SUMIF(order_details__2[SupplierID],suppliers[[#This Row],[SupplierID]],order_details__2[Quantity]) -> 1436
A13: 12 | B13: Plutzer Lebensmittelgromrkte AG | C13: Martin Bein | D13: International Marketing Mgr. | E13: Bogenallee 51 | F13: Frankfurt | G13: NULL | H13: 60439 | I13: Germany | J13: (069) 992755 | K13: NULL | L13: =SUMIF(products[SupplierID],suppliers[[#This Row],[SupplierID]],products[[Product Sale ]]) -> 155946.55 | M13: =SUMIF(order_details__2[SupplierID],suppliers[[#This Row],[SupplierID]],order_details__2[Quantity]) -> 4072
... A30: 29 | B30: Forts d'rables | C30: Chantal Goulet | D30: Accounting Manager | E30: 148 rue Chasseur | F30: Ste-Hyacinthe | G30: Qubec | H30: J2S 7S8 | I30: Canada | J30: (514) 555-2955 | K30: (514) 555-2921 | L30: =SUMIF(products[SupplierID],suppliers[[#This Row],[SupplierID]],products[[Product Sale ]]) -> 66266.7 | M30: =SUMIF(order_details__2[SupplierID],suppliers[[#This Row],[SupplierID]],order_details__2[Quantity]) -> 1686

Sheet supplier_pivot
A3: Row Labels | B3: Sum of Quantity Supplied | I3: *
A4: Leka Trading | B4: 1878
A5: New England Seafood Cannery | B5: 2084
A6: G'day, Mate | B6: 2108
A7: Exotic Liquids | B7: 2213
A8: Formaggi Fortini s.r.l. | B8: 2500
A9: Norske Meierier | B9: 2526
A10: Specialty Biscuits, Ltd. | B10: 2851
A11: Gai pturage | B11: 3073
A12: Pavlova, Ltd. | B12: 3937
A13: Plutzer Lebensmittelgromrkte AG | B13: 4072
A14: Grand Total | B14: 27242
A36: Row Labels | B36: Sum of Supplier Sale
A37: Norske Meierier | B37: 46897.2
A38: Specialty Biscuits, Ltd. | B38: 48793.8
A39: Formaggi Fortini s.r.l. | B39: 51082.5
A40: Pasta Buttini s.r.l. | B40: 52929
A41: Forts d'rables | B41: 66266.7
A42: G'day, Mate | B42: 69636.6
A43: Pavlova, Ltd. | B43: 115386.05
A44: Gai pturage | B44: 126582
A45: Plutzer Lebensmittelgromrkte AG | B45: 155946.55
A46: Aux joyeux ecclsiastiques | B46: 163135
A47: Grand Total | B47: 896655.4

Sheet shippers
A1: ShipperID | B1: CompanyName | C1: Phone | D1: Products Supplied | E1: Total Freight
A2: 1 | B2: Speedy Express | C2: (503) 555-9831 | D2: =SUMIF(Table15[ShipID],shippers[[#This Row],[ShipperID]],Table15[[OrderQuantity ]]) -> 15919 | E2: =SUMIF(orders[ShipVia],shippers[[#This Row],[ShipperID]],orders[Freight]) -> 16185.33
A3: 2 | B3: United Package | C3: (503) 555-3199 | D3: =SUMIF(Table15[ShipID],shippers[[#This Row],[ShipperID]],Table15[[OrderQuantity ]]) -> 19945 | E3: =SUMIF(orders[ShipVia],shippers[[#This Row],[ShipperID]],orders[Freight]) -> 28230.88
A4: 3 | B4: Federal Shipping | C4: (503) 555-9931 | D4: =SUMIF(Table15[ShipID],shippers[[#This Row],[ShipperID]],Table15[[OrderQuantity ]]) -> 15453 | E4: =SUMIF(orders[ShipVia],shippers[[#This Row],[ShipperID]],orders[Freight]) -> 20512.51

Sheet region
A1: RegionID | B1: RegionDescription
A2: 1 | B2: Eastern
A3: 2 | B3: Westerns
A4: 3 | B4: Northern
A5: 4 | B5: Southern

Sheet products
A1: ProductID | B1: ProductName | C1: SupplierID | D1: CategoryID | E1: QuantityPerUnit | F1: UnitPrice | G1: UnitsInStock | H1: UnitsOnOrder | I1: ReorderLevel | J1: Discontinued | K1: Product Sale | L1: QuantitySale
A2: 1 | B2: Chai | C2: 1 | D2: 1 | E2: 10 boxes x 20 bags | F2: 18 | G2: 39 | H2: 0 | I2: 10 | J2: 0 | K2: =SUMIF(order_details__2[ProductID],products[[#This Row],[ProductID]],order_details__2[Line Sale]) -> 14277.6 | L2: =SUMIF(order_details__2[ProductID],products[[#This Row],[ProductID]],order_details__2[Quantity]) -> 828
A3: 2 | B3: Chang | C3: 1 | D3: 1 | E3: 24 - 12 oz bottles | F3: 19 | G3: 17 | H3: 40 | I3: 25 | J3: 0 | K3: =SUMIF(order_details__2[ProductID],products[[#This Row],[ProductID]],order_details__2[Line Sale]) -> 18559.2 | L3: =SUMIF(order_details__2[ProductID],products[[#This Row],[ProductID]],order_details__2[Quantity]) -> 1057
A4: 3 | B4: Aniseed Syrup | C4: 1 | D4: 2 | E4: 12 - 550 ml bottles | F4: 10 | G4: 13 | H4: 70 | I4: 25 | J4: 0 | K4: =SUMIF(order_details__2[ProductID],products[[#This Row],[ProductID]],order_details__2[Line Sale]) -> 3080 | L4: =SUMIF(order_details__2[ProductID],products[[#This Row],[ProductID]],order_details__2[Quantity]) -> 328
A5: 4 | B5: Chef Anton's Cajun Seasoning | C5: 2 | D5: 2 | E5: 48 - 6 oz jars | F5: 22 | G5: 53 | H5: 0 | I5: 0 | J5: 0 | K5: =SUMIF(order_details__2[ProductID],products[[#This Row],[ProductID]],order_details__2[Line Sale]) -> 9424.8 | L5: =SUMIF(order_details__2[ProductID],products[[#This Row],[ProductID]],order_details__2[Quantity]) -> 453
A6: 5 | B6: Chef Anton's Gumbo Mix | C6: 2 | D6: 2 | E6: 36 boxes | F6: 21.35 | G6: 0 | H6: 0 | I6: 0 | J6: 1 | K6: =SUMIF(order_details__2[ProductID],products[[#This Row],[ProductID]],order_details__2[Line Sale]) -> 5801.15 | L6: =SUMIF(order_details__2[ProductID],products[[#This Row],[ProductID]],order_details__2[Quantity]) -> 298
A7: 6 | B7: Grandma's Boysenberry Spread | C7: 3 | D7: 2 | E7: 12 - 8 oz jars | F7: 25 | G7: 120 | H7: 0 | I7: 25 | J7: 0 | K7: =SUMIF(order_details__2[ProductID],products[[#This Row],[ProductID]],order_details__2[Line Sale]) -> 7345 | L7: =SUMIF(order_details__2[ProductID],products[[#This Row],[ProductID]],order_details__2[Quantity]) -> 301
A8: 7 | B8: Uncle Bob's Organic Dried Pears | C8: 3 | D8: 7 | E8: 12 - 1 lb pkgs. | F8: 30 | G8: 15 | H8: 0 | I8: 10 | J8: 0 | K8: =SUMIF(order_details__2[ProductID],products[[#This Row],[ProductID]],order_details__2[Line Sale]) -> 22464 | L8: =SUMIF(order_details__2[ProductID],products[[#This Row],[ProductID]],order_details__2[Quantity]) -> 763
A9: 8 | B9: Northwoods Cranberry Sauce | C9: 3 | D9: 2 | E9: 12 - 12 oz jars | F9: 40 | G9: 6 | H9: 0 | I9: 0 | J9: 0 | K9: =SUMIF(order_details__2[ProductID],products[[#This Row],[ProductID]],order_details__2[Line Sale]) -> 13760 | L9: =SUMIF(order_details__2[ProductID],products[[#This Row],[ProductID]],order_details__2[Quantity]) -> 372
A10: 9 | B10: Mishi Kobe Niku | C10: 4 | D10: 6 | E10: 18 - 500 g pkgs. | F10: 97 | G10: 29 | H10: 0 | I10: 0 | J10: 1 | K10: =SUMIF(order_details__2[ProductID],products[[#This Row],[ProductID]],order_details__2[Line Sale]) -> 8827 | L10: =SUMIF(order_details__2[ProductID],products[[#This Row],[ProductID]],order_details__2[Quantity]) -> 95
A11: 10 | B11: Ikura | C11: 4 | D11: 8 | E11: 12 - 200 ml jars | F11: 31 | G11: 31 | H11: 0 | I11: 0 | J11: 0 | K11: =SUMIF(order_details__2[ProductID],products[[#This Row],[ProductID]],order_details__2[Line Sale]) -> 22140.2 | L11: =SUMIF(order_details__2[ProductID],products[[#This Row],[ProductID]],order_details__2[Quantity]) -> 742
A12: 11 | B12: Queso Cabrales | C12: 5 | D12: 4 | E12: 1 kg pkg. | F12: 21 | G12: 22 | H12: 30 | I12: 30 | J12: 0 | K12: =SUMIF(order_details__2[ProductID],products[[#This Row],[ProductID]],order_details__2[Line Sale]) -> 13902 | L12: =SUMIF(order_details__2[ProductID],products[[#This Row],[ProductID]],order_details__2[Quantity]) -> 706
A13: 12 | B13: Queso Manchego La Pastora | C13: 5 | D13: 4 | E13: 10 - 500 g pkgs. | F13: 38 | G13: 86 | H13: 0 | I13: 0 | J13: 0 | K13: =SUMIF(order_details__2[ProductID],products[[#This Row],[ProductID]],order_details__2[Line Sale]) -> 12866.8 | L13: =SUMIF(order_details__2[ProductID],products[[#This Row],[ProductID]],order_details__2[Quantity]) -> 344
... A78: 77 | B78: Original Frankfurter grne Soe | C78: 12 | D78: 2 | E78: 12 boxes | F78: 13 | G78: 32 | H78: 0 | I78: 15 | J78: 0 | K78: =SUMIF(order_details__2[ProductID],products[[#This Row],[ProductID]],order_details__2[Line Sale]) -> 9685 | L78: =SUMIF(order_details__2[ProductID],products[[#This Row],[ProductID]],order_details__2[Quantity]) -> 791

Sheet product_pivot
A3: Row Labels | B3: Sum of QuantitySale
A4: Flotemysost | B4: 1057
A5: Chang | B5: 1057
A6: Tarte au sucre | B6: 1083
A7: Boston Crab Meat | B7: 1103
A8: Guaran Fantstica | B8: 1125
A9: Rhnbru Klosterbier | B9: 1155
A10: Pavlova | B10: 1158
A11: Gnocchi di nonna Alice | B11: 1263
A12: Gorgonzola Telino | B12: 1397
A13: Raclette Courdavault | B13: 1496
A14: Camembert Pierrot | B14: 1577
A15: Grand Total | B15: 13471
A23: Row Labels | B23: Sum of Product Sale
A24: Rssle Sauerkraut | B24: 26865.6
A25: Carnarvon Tigers | B25: 31987.5
A26: Alice Mutton | B26: 35482.2
A27: Manjimup Dried Apples | B27: 44742.6
A28: Gnocchi di nonna Alice | B28: 45121.2
A29: Tarte au sucre | B29: 49827.9
A30: Camembert Pierrot | B30: 50286
A31: Raclette Courdavault | B31: 76296
A32: Thringer Rostbratwurst | B32: 87736.4
A33: Cte de Blaye | B33: 149984.2
A34: Grand Total | B34: 598329.6

Sheet orders
A1: OrderID | B1: CustomerID | C1: EmployeeID | D1: OrderDate | E1: RequiredDate | F1: ShippedDate | G1: ShipVia | H1: Freight | I1: ShipName | J1: ShipAddress | K1: ShipCity | L1: ShipRegion | M1: ShipPostalCode | N1: ShipCountry | O1: OrderQuantity | P1: Order Sale | Q1: Territory | R1: Region | S1: Shipper | T1: Year | U1: Month
A2: 10248 | B2: VINET | C2: 5 | D2: 35250 | E2: 35278 | F2: 35262 | G2: 3 | H2: 32.38 | I2: Vins et alcools Chevalier | J2: 59 rue de l-Abbaye | K2: Reims | L2: NULL | M2: 51100 | N2: France | O2: =VLOOKUP(orders[[#This Row],[OrderID]],Table15[],4,FALSE) -> 27 | P2: =VLOOKUP(orders[[#This Row],[OrderID]],Table15[],2,FALSE) -> 440 | Q2: =VLOOKUP(orders[[#This Row],[EmployeeID]],employee_territory[],2,FALSE) -> 2903 | R2: =VLOOKUP(orders[[#This Row],[Territory]],territories[],4,FALSE) -> Eastern | S2: =VLOOKUP(orders[[#This Row],[ShipVia]],shippers[],2,FALSE) -> Federal Shipping | T2: =YEAR(orders[[#This Row],[OrderDate]]) -> 1996 | U2: =MONTH(orders[[#This Row],[OrderDate]]) -> 7
A3: 10249 | B3: TOMSP | C3: 6 | D3: 35251 | E3: 35293 | F3: 35256 | G3: 1 | H3: 11.61 | I3: Toms Spezialitten | J3: Luisenstr. 48 | K3: Mnster | L3: NULL | M3: 44087 | N3: Germany | O3: =VLOOKUP(orders[[#This Row],[OrderID]],Table15[],4,FALSE) -> 49 | P3: =VLOOKUP(orders[[#This Row],[OrderID]],Table15[],2,FALSE) -> 1863.4 | Q3: =VLOOKUP(orders[[#This Row],[EmployeeID]],employee_territory[],2,FALSE) -> 85014 | R3: =VLOOKUP(orders[[#This Row],[Territory]],territories[],4,FALSE) -> Westerns | S3: =VLOOKUP(orders[[#This Row],[ShipVia]],shippers[],2,FALSE) -> Speedy Express | T3: =YEAR(orders[[#This Row],[OrderDate]]) -> 1996 | U3: =MONTH(orders[[#This Row],[OrderDate]]) -> 7
A4: 10250 | B4: HANAR | C4: 4 | D4: 35254 | E4: 35282 | F4: 35258 | G4: 2 | H4: 65.83 | I4: Hanari Carnes | J4: Rua do Pao, 67 | K4: Rio de Janeiro | L4: RJ | M4: 05454-876 | N4: Brazil | O4: =VLOOKUP(orders[[#This Row],[OrderID]],Table15[],4,FALSE) -> 60 | P4: =VLOOKUP(orders[[#This Row],[OrderID]],Table15[],2,FALSE) -> 1813 | Q4: =VLOOKUP(orders[[#This Row],[EmployeeID]],employee_territory[],2,FALSE) -> 20852 | R4: =VLOOKUP(orders[[#This Row],[Territory]],territories[],4,FALSE) -> Eastern | S4: =VLOOKUP(orders[[#This Row],[ShipVia]],shippers[],2,FALSE) -> United Package | T4: =YEAR(orders[[#This Row],[OrderDate]]) -> 1996 | U4: =MONTH(orders[[#This Row],[OrderDate]]) -> 7
A5: 10251 | B5: VICTE | C5: 3 | D5: 35254 | E5: 35282 | F5: 35261 | G5: 1 | H5: 41.34 | I5: Victuailles en stock | J5: 2, rue du Commerce | K5: Lyon | L5: NULL | M5: 69004 | N5: France | O5: =VLOOKUP(orders[[#This Row],[OrderID]],Table15[],4,FALSE) -> 41 | P5: =VLOOKUP(orders[[#This Row],[OrderID]],Table15[],2,FALSE) -> 670.8 | Q5: =VLOOKUP(orders[[#This Row],[EmployeeID]],employee_territory[],2,FALSE) -> 30346 | R5: =VLOOKUP(orders[[#This Row],[Territory]],territories[],4,FALSE) -> Southern | S5: =VLOOKUP(orders[[#This Row],[ShipVia]],shippers[],2,FALSE) -> Speedy Express | T5: =YEAR(orders[[#This Row],[OrderDate]]) -> 1996 | U5: =MONTH(orders[[#This Row],[OrderDate]]) -> 7
A6: 10252 | B6: SUPRD | C6: 4 | D6: 35255 | E6: 35283 | F6: 35257 | G6: 2 | H6: 51.3 | I6: Suprmes dlices | J6: Boulevard Tirou, 255 | K6: Charleroi | L6: NULL | M6: B-6000 | N6: Belgium | O6: =VLOOKUP(orders[[#This Row],[OrderID]],Table15[],4,FALSE) -> 105 | P6: =VLOOKUP(orders[[#This Row],[OrderID]],Table15[],2,FALSE) -> 3730 | Q6: =VLOOKUP(orders[[#This Row],[EmployeeID]],employee_territory[],2,FALSE) -> 20852 | R6: =VLOOKUP(orders[[#This Row],[Territory]],territories[],4,FALSE) -> Eastern | S6: =VLOOKUP(orders[[#This Row],[ShipVia]],shippers[],2,FALSE) -> United Package | T6: =YEAR(orders[[#This Row],[OrderDate]]) -> 1996 | U6: =MONTH(orders[[#This Row],[OrderDate]]) -> 7
A7: 10253 | B7: HANAR | C7: 3 | D7: 35256 | E7: 35270 | F7: 35262 | G7: 2 | H7: 58.17 | I7: Hanari Carnes | J7: Rua do Pao, 67 | K7: Rio de Janeiro | L7: RJ | M7: 05454-876 | N7: Brazil | O7: =VLOOKUP(orders[[#This Row],[OrderID]],Table15[],4,FALSE) -> 102 | P7: =VLOOKUP(orders[[#This Row],[OrderID]],Table15[],2,FALSE) -> 1444.8 | Q7: =VLOOKUP(orders[[#This Row],[EmployeeID]],employee_territory[],2,FALSE) -> 30346 | R7: =VLOOKUP(orders[[#This Row],[Territory]],territories[],4,FALSE) -> Southern | S7: =VLOOKUP(orders[[#This Row],[ShipVia]],shippers[],2,FALSE) -> United Package | T7: =YEAR(orders[[#This Row],[OrderDate]]) -> 1996 | U7: =MONTH(orders[[#This Row],[OrderDate]]) -> 7
A8: 10254 | B8: CHOPS | C8: 5 | D8: 35257 | E8: 35285 | F8: 35269 | G8: 2 | H8: 22.98 | I8: Chop-suey Chinese | J8: Hauptstr. 31 | K8: Bern | L8: NULL | M8: 3012 | N8: Switzerland | O8: =VLOOKUP(orders[[#This Row],[OrderID]],Table15[],4,FALSE) -> 57 | P8: =VLOOKUP(orders[[#This Row],[OrderID]],Table15[],2,FALSE) -> 625.2 | Q8: =VLOOKUP(orders[[#This Row],[EmployeeID]],employee_territory[],2,FALSE) -> 2903 | R8: =VLOOKUP(orders[[#This Row],[Territory]],territories[],4,FALSE) -> Eastern | S8: =VLOOKUP(orders[[#This Row],[ShipVia]],shippers[],2,FALSE) -> United Package | T8: =YEAR(orders[[#This Row],[OrderDate]]) -> 1996 | U8: =MONTH(orders[[#This Row],[OrderDate]]) -> 7
A9: 10255 | B9: RICSU | C9: 9 | D9: 35258 | E9: 35286 | F9: 35261 | G9: 3 | H9: 148.33 | I9: Richter Supermarkt | J9: Starenweg 5 | K9: Genve | L9: NULL | M9: 1204 | N9: Switzerland | O9: =VLOOKUP(orders[[#This Row],[OrderID]],Table15[],4,FALSE) -> 110 | P9: =VLOOKUP(orders[[#This Row],[OrderID]],Table15[],2,FALSE) -> 2490.5 | Q9: =VLOOKUP(orders[[#This Row],[EmployeeID]],employee_territory[],2,FALSE) -> 3049 | R9: =VLOOKUP(orders[[#This Row],[Territory]],territories[],4,FALSE) -> Northern | S9: =VLOOKUP(orders[[#This Row],[ShipVia]],shippers[],2,FALSE) -> Federal Shipping | T9: =YEAR(orders[[#This Row],[OrderDate]]) -> 1996 | U9: =MONTH(orders[[#This Row],[OrderDate]]) -> 7
A10: 10256 | B10: WELLI | C10: 3 | D10: 35261 | E10: 35289 | F10: 35263 | G10: 2 | I10: Wellington Importadora | J10: Rua do Mercado, 12 | K10: Resende | L10: SP | M10: 08737-363 | N10: Brazil | O10: =VLOOKUP(orders[[#This Row],[OrderID]],Table15[],4,FALSE) -> 27 | P10: =VLOOKUP(orders[[#This Row],[OrderID]],Table15[],2,FALSE) -> 517.8 | Q10: =VLOOKUP(orders[[#This Row],[EmployeeID]],employee_territory[],2,FALSE) -> 30346 | R10: =VLOOKUP(orders[[#This Row],[Territory]],territories[],4,FALSE) -> Southern | S10: =VLOOKUP(orders[[#This Row],[ShipVia]],shippers[],2,FALSE) -> United Package | T10: =YEAR(orders[[#This Row],[OrderDate]]) -> 1996 | U10: =MONTH(orders[[#This Row],[OrderDate]]) -> 7
A11: 10257 | B11: HILAA | C11: 4 | D11: 35262 | E11: 35290 | F11: 35268 | G11: 3 | H11: 81.91 | I11: HILARION-Abastos | J11: Carrera 22 con Ave. Carlos Soublette #8-35 | K11: San Cristbal | L11: Tchira | M11: 5022 | N11: Venezuela | O11: =VLOOKUP(orders[[#This Row],[OrderID]],Table15[],4,FALSE) -> 46 | P11: =VLOOKUP(orders[[#This Row],[OrderID]],Table15[],2,FALSE) -> 1119.9 | Q11: =VLOOKUP(orders[[#This Row],[EmployeeID]],employee_territory[],2,FALSE) -> 20852 | R11: =VLOOKUP(orders[[#This Row],[Territory]],territories[],4,FALSE) -> Eastern | S11: =VLOOKUP(orders[[#This Row],[ShipVia]],shippers[],2,FALSE) -> Federal Shipping | T11: =YEAR(orders[[#This Row],[OrderDate]]) -> 1996 | U11: =MONTH(orders[[#This Row],[OrderDate]]) -> 7
A12: 10258 | B12: ERNSH | C12: 1 | D12: 35263 | E12: 35291 | F12: 35269 | G12: 1 | H12: 140.51 | I12: Ernst Handel | J12: Kirchgasse 6 | K12: Graz | L12: NULL | M12: 8010 | N12: Austria | O12: =VLOOKUP(orders[[#This Row],[OrderID]],Table15[],4,FALSE) -> 121 | P12: =VLOOKUP(orders[[#This Row],[OrderID]],Table15[],2,FALSE) -> 2018.6 | Q12: =VLOOKUP(orders[[#This Row],[EmployeeID]],employee_territory[],2,FALSE) -> 6897 | R12: =VLOOKUP(orders[[#This Row],[Territory]],territories[],4,FALSE) -> Eastern | S12: =VLOOKUP(orders[[#This Row],[ShipVia]],shippers[],2,FALSE) -> Speedy Express | T12: =YEAR(orders[[#This Row],[OrderDate]]) -> 1996 | U12: =MONTH(orders[[#This Row],[OrderDate]]) -> 7
A13: 10259 | B13: CENTC | C13: 4 | D13: 35264 | E13: 35292 | F13: 35271 | G13: 3 | H13: 3.25 | I13: Centro comercial Moctezuma | J13: Sierras de Granada 9993 | K13: Mxico D.F. | L13: NULL | M13: 5022 | N13: Mexico | O13: =VLOOKUP(orders[[#This Row],[OrderID]],Table15[],4,FALSE) -> 11 | P13: =VLOOKUP(orders[[#This Row],[OrderID]],Table15[],2,FALSE) -> 100.8 | Q13: =VLOOKUP(orders[[#This Row],[EmployeeID]],employee_territory[],2,FALSE) -> 20852 | R13: =VLOOKUP(orders[[#This Row],[Territory]],territories[],4,FALSE) -> Eastern | S13: =VLOOKUP(orders[[#This Row],[ShipVia]],shippers[],2,FALSE) -> Federal Shipping | T13: =YEAR(orders[[#This Row],[OrderDate]]) -> 1996 | U13: =MONTH(orders[[#This Row],[OrderDate]]) -> 7
A14: 10260 | B14: OTTIK | C14: 4 | D14: 35265 | E14: 35293 | F14: 35275 | G14: 1 | H14: 55.09 | I14: Ottilies Kseladen | J14: Mehrheimerstr. 369 | K14: Kln | L14: NULL | M14: 50739 | N14: Germany | O14: =VLOOKUP(orders[[#This Row],[OrderID]],Table15[],4,FALSE) -> 102 | P14: =VLOOKUP(orders[[#This Row],[OrderID]],Table15[],2,FALSE) -> 1746.2 | Q14: =VLOOKUP(orders[[#This Row],[EmployeeID]],employee_territory[],2,FALSE) -> 20852 | R14: =VLOOKUP(orders[[#This Row],[Territory]],territories[],4,FALSE) -> Eastern | S14: =VLOOKUP(orders[[#This Row],[ShipVia]],shippers[],2,FALSE) -> Speedy Express | T14: =YEAR(orders[[#This Row],[OrderDate]]) -> 1996 | U14: =MONTH(orders[[#This Row],[OrderDate]]) -> 7
A15: 10261 | B15: QUEDE | C15: 4 | D15: 35265 | E15: 35293 | F15: 35276 | G15: 2 | H15: 3.05 | I15: Que Delcia | J15: Rua da Panificadora, 12 | K15: Rio de Janeiro | L15: RJ | M15: 02389-673 | N15: Brazil | O15: =VLOOKUP(orders[[#This Row],[OrderID]],Table15[],4,FALSE) -> 40 | P15: =VLOOKUP(orders[[#This Row],[OrderID]],Table15[],2,FALSE) -> 448 | Q15: =VLOOKUP(orders[[#This Row],[EmployeeID]],employee_territory[],2,FALSE) -> 20852 | R15: =VLOOKUP(orders[[#This Row],[Territory]],territories[],4,FALSE) -> Eastern | S15: =VLOOKUP(orders[[#This Row],[ShipVia]],shippers[],2,FALSE) -> United Package | T15: =YEAR(orders[[#This Row],[OrderDate]]) -> 1996 | U15: =MONTH(orders[[#This Row],[OrderDate]]) -> 7
A16: 10262 | B16: RATTC | C16: 8 | D16: 35268 | E16: 35296 | F16: 35271 | G16: 3 | H16: 48.29 | I16: Rattlesnake Canyon Grocery | J16: 2817 Milton Dr. | K16: Albuquerque | L16: NM | M16: 87110 | N16: USA | O16: =VLOOKUP(orders[[#This Row],[OrderID]],Table15[],4,FALSE) -> 29 | P16: =VLOOKUP(orders[[#This Row],[OrderID]],Table15[],2,FALSE) -> 624.8 | Q16: =VLOOKUP(orders[[#This Row],[EmployeeID]],employee_territory[],2,FALSE) -> 19428 | R16: =VLOOKUP(orders[[#This Row],[Territory]],territories[],4,FALSE) -> Northern | S16: =VLOOKUP(orders[[#This Row],[ShipVia]],shippers[],2,FALSE) -> Federal Shipping | T16: =YEAR(orders[[#This Row],[OrderDate]]) -> 1996 | U16: =MONTH(orders[[#This Row],[OrderDate]]) -> 7
A17: 10263 | B17: ERNSH | C17: 9 | D17: 35269 | E17: 35297 | F17: 35277 | G17: 3 | H17: 146.06 | I17: Ernst Handel | J17: Kirchgasse 6 | K17: Graz | L17: NULL | M17: 8010 | N17: Austria | O17: =VLOOKUP(orders[[#This Row],[OrderID]],Table15[],4,FALSE) -> 184 | P17: =VLOOKUP(orders[[#This Row],[OrderID]],Table15[],2,FALSE) -> 2464.8 | Q17: =VLOOKUP(orders[[#This Row],[EmployeeID]],employee_territory[],2,FALSE) -> 3049 | R17: =VLOOKUP(orders[[#This Row],[Territory]],territories[],4,FALSE) -> Northern | S17: =VLOOKUP(orders[[#This Row],[ShipVia]],shippers[],2,FALSE) -> Federal Shipping | T17: =YEAR(orders[[#This Row],[OrderDate]]) -> 1996 | U17: =MONTH(orders[[#This Row],[OrderDate]]) -> 7
A18: 10264 | B18: FOLKO | C18: 6 | D18: 35270 | E18: 35298 | F18: 35300 | G18: 3 | H18: 3.67 | I18: Folk och f HB | J18: kergatan 24 | K18: Brcke | L18: NULL | M18: S-844 67 | N18: Sweden | O18: =VLOOKUP(orders[[#This Row],[OrderID]],Table15[],4,FALSE) -> 60 | P18: =VLOOKUP(orders[[#This Row],[OrderID]],Table15[],2,FALSE) -> 724.5 | Q18: =VLOOKUP(orders[[#This Row],[EmployeeID]],employee_territory[],2,FALSE) -> 85014 | R18: =VLOOKUP(orders[[#This Row],[Territory]],territories[],4,FALSE) -> Westerns | S18: =VLOOKUP(orders[[#This Row],[ShipVia]],shippers[],2,FALSE) -> Federal Shipping | T18: =YEAR(orders[[#This Row],[OrderDate]]) -> 1996 | U18: =MONTH(orders[[#This Row],[OrderDate]]) -> 7
A19: 10265 | B19: BLONP | C19: 2 | D19: 35271 | E19: 35299 | F19: 35289 | G19: 1 | H19: 55.28 | I19: Blondel pre et fils | J19: 24, place Klber | K19: Strasbourg | L19: NULL | M19: 67000 | N19: France | O19: =VLOOKUP(orders[[#This Row],[OrderID]],Table15[],4,FALSE) -> 50 | P19: =VLOOKUP(orders[[#This Row],[OrderID]],Table15[],2,FALSE) -> 1176 | Q19: =VLOOKUP(orders[[#This Row],[EmployeeID]],employee_territory[],2,FALSE) -> 1581 | R19: =VLOOKUP(orders[[#This Row],[Territory]],territories[],4,FALSE) -> Eastern | S19: =VLOOKUP(orders[[#This Row],[ShipVia]],shippers[],2,FALSE) -> Speedy Express | T19: =YEAR(orders[[#This Row],[OrderDate]]) -> 1996 | U19: =MONTH(orders[[#This Row],[OrderDate]]) -> 7
A20: 10266 | B20: WARTH | C20: 3 | D20: 35272 | E20: 35314 | F20: 35277 | G20: 3 | H20: 25.73 | I20: Wartian Herkku | J20: Torikatu 38 | K20: Oulu | L20: NULL | M20: 90110 | N20: Finland | O20: =VLOOKUP(orders[[#This Row],[OrderID]],Table15[],4,FALSE) -> 12 | P20: =VLOOKUP(orders[[#This Row],[OrderID]],Table15[],2,FALSE) -> 364.8 | Q20: =VLOOKUP(orders[[#This Row],[EmployeeID]],employee_territory[],2,FALSE) -> 30346 | R20: =VLOOKUP(orders[[#This Row],[Territory]],territories[],4,FALSE) -> Southern | S20: =VLOOKUP(orders[[#This Row],[ShipVia]],shippers[],2,FALSE) -> Federal Shipping | T20: =YEAR(orders[[#This Row],[OrderDate]]) -> 1996 | U20: =MONTH(orders[[#This Row],[OrderDate]]) -> 7
A21: 10267 | B21: FRANK | C21: 4 | D21: 35275 | E21: 35303 | F21: 35283 | G21: 1 | H21: 208.58 | I21: Frankenversand | J21: Berliner Platz 43 | K21: Mnchen | L21: NULL | M21: 80805 | N21: Germany | O21: =VLOOKUP(orders[[#This Row],[OrderID]],Table15[],4,FALSE) -> 135 | P21: =VLOOKUP(orders[[#This Row],[OrderID]],Table15[],2,FALSE) -> 4031 | Q21: =VLOOKUP(orders[[#This Row],[EmployeeID]],employee_territory[],2,FALSE) -> 20852 | R21: =VLOOKUP(orders[[#This Row],[Territory]],territories[],4,FALSE) -> Eastern | S21: =VLOOKUP(orders[[#This Row],[ShipVia]],shippers[],2,FALSE) -> Speedy Express | T21: =YEAR(orders[[#This Row],[OrderDate]]) -> 1996 | U21: =MONTH(orders[[#This Row],[OrderDate]]) -> 7
A22: 10268 | B22: GROSR | C22: 8 | D22: 35276 | E22: 35304 | F22: 35279 | G22: 3 | H22: 66.29 | I22: GROSELLA-Restaurante | J22: 5 Ave. Los Palos Grandes | K22: Caracas | L22: DF | M22: 1081 | N22: Venezuela | O22: =VLOOKUP(orders[[#This Row],[OrderID]],Table15[],4,FALSE) -> 14 | P22: =VLOOKUP(orders[[#This Row],[OrderID]],Table15[],2,FALSE) -> 1101.2 | Q22: =VLOOKUP(orders[[#This Row],[EmployeeID]],employee_territory[],2,FALSE) -> 19428 | R22: =VLOOKUP(orders[[#This Row],[Territory]],territories[],4,FALSE) -> Northern | S22: =VLOOKUP(orders[[#This Row],[ShipVia]],shippers[],2,FALSE) -> Federal Shipping | T22: =YEAR(orders[[#This Row],[OrderDate]]) -> 1996 | U22: =MONTH(orders[[#This Row],[OrderDate]]) -> 7
... A761: 11007 | B761: PRINI | C761: 8 | D761: 35893 | E761: 35921 | F761: 35898 | G761: 2 | H761: 202.24 | I761: Princesa Isabel Vinhos | J761: Estrada da sade n. 58 | K761: Lisboa | L761: NULL | M761: 1756 | N761: Portugal | O761: =VLOOKUP(orders[[#This Row],[OrderID]],Table15[],4,FALSE) -> 54 | P761: =VLOOKUP(orders[[#This Row],[OrderID]],Table15[],2,FALSE) -> 2633.9 | Q761: =VLOOKUP(orders[[#This Row],[EmployeeID]],employee_territory[],2,FALSE) -> 19428 | R761: =VLOOKUP(orders[[#This Row],[Territory]],territories[],4,FALSE) -> Northern | S761: =VLOOKUP(orders[[#This Row],[ShipVia]],shippers[],2,FALSE) -> United Package | T761: =YEAR(orders[[#This Row],[OrderDate]]) -> 1998 | U761: =MONTH(orders[[#This Row],[OrderDate]]) -> 4
A762: 11008 | B762: ERNSH | C762: 7 | D762: 35893 | E762: 35921 | G762: 3 | H762: 79.46 | I762: Ernst Handel | J762: Kirchgasse 6 | K762: Graz | L762: NULL | M762: 8010 | N762: Austria | O762: =VLOOKUP(orders[[#This Row],[OrderID]],Table15[],4,FALSE) -> 181 | P762: =VLOOKUP(orders[[#This Row],[OrderID]],Table15[],2,FALSE) -> 4903.5 | Q762: =VLOOKUP(orders[[#This Row],[EmployeeID]],employee_territory[],2,FALSE) -> 60179 | R762: =VLOOKUP(orders[[#This Row],[Territory]],territories[],4,FALSE) -> Westerns | S762: =VLOOKUP(orders[[#This Row],[ShipVia]],shippers[],2,FALSE) -> Federal Shipping | T762: =YEAR(orders[[#This Row],[OrderDate]]) -> 1998 | U762: =MONTH(orders[[#This Row],[OrderDate]]) -> 4
A763: 11009 | B763: GODOS | C763: 2 | D763: 35893 | E763: 35921 | F763: 35895 | G763: 1 | H763: 59.11 | I763: Godos Cocina Tpica | J763: C/ Romero, 33 | K763: Sevilla | L763: NULL | M763: 41101 | N763: Spain | O763: =VLOOKUP(orders[[#This Row],[OrderID]],Table15[],4,FALSE) -> 39 | P763: =VLOOKUP(orders[[#This Row],[OrderID]],Table15[],2,FALSE) -> 702 | Q763: =VLOOKUP(orders[[#This Row],[EmployeeID]],employee_territory[],2,FALSE) -> 1581 | R763: =VLOOKUP(orders[[#This Row],[Territory]],territories[],4,FALSE) -> Eastern | S763: =VLOOKUP(orders[[#This Row],[ShipVia]],shippers[],2,FALSE) -> Speedy Express | T763: =YEAR(orders[[#This Row],[OrderDate]]) -> 1998 | U763: =MONTH(orders[[#This Row],[OrderDate]]) -> 4
A764: 11010 | B764: REGGC | C764: 2 | D764: 35894 | E764: 35922 | F764: 35906 | G764: 2 | H764: 28.71 | I764: Reggiani Caseifici | J764: Strada Provinciale 124 | K764: Reggio Emilia | L764: NULL | M764: 42100 | N764: Italy | O764: =VLOOKUP(orders[[#This Row],[OrderID]],Table15[],4,FALSE) -> 30 | P764: =VLOOKUP(orders[[#This Row],[OrderID]],Table15[],2,FALSE) -> 645 | Q764: =VLOOKUP(orders[[#This Row],[EmployeeID]],employee_territory[],2,FALSE) -> 1581 | R764: =VLOOKUP(orders[[#This Row],[Territory]],territories[],4,FALSE) -> Eastern | S764: =VLOOKUP(orders[[#This Row],[ShipVia]],shippers[],2,FALSE) -> United Package | T764: =YEAR(orders[[#This Row],[OrderDate]]) -> 1998 | U764: =MONTH(orders[[#This Row],[OrderDate]]) -> 4
A765: 11011 | B765: ALFKI | C765: 3 | D765: 35894 | E765: 35922 | F765: 35898 | G765: 1 | H765: 1.21 | I765: Alfred-s Futterkiste | J765: Obere Str. 57 | K765: Berlin | L765: NULL | M765: 12209 | N765: Germany | O765: =VLOOKUP(orders[[#This Row],[OrderID]],Table15[],4,FALSE) -> 60 | P765: =VLOOKUP(orders[[#This Row],[OrderID]],Table15[],2,FALSE) -> 960 | Q765: =VLOOKUP(orders[[#This Row],[EmployeeID]],employee_territory[],2,FALSE) -> 30346 | R765: =VLOOKUP(orders[[#This Row],[Territory]],territories[],4,FALSE) -> Southern | S765: =VLOOKUP(orders[[#This Row],[ShipVia]],shippers[],2,FALSE) -> Speedy Express | T765: =YEAR(orders[[#This Row],[OrderDate]]) -> 1998 | U765: =MONTH(orders[[#This Row],[OrderDate]]) -> 4
A766: 11012 | B766: FRANK | C766: 1 | D766: 35894 | E766: 35908 | F766: 35902 | G766: 3 | H766: 242.95 | I766: Frankenversand | J766: Berliner Platz 43 | K766: Mnchen | L766: NULL | M766: 80805 | N766: Germany | O766: =VLOOKUP(orders[[#This Row],[OrderID]],Table15[],4,FALSE) -> 146 | P766: =VLOOKUP(orders[[#This Row],[OrderID]],Table15[],2,FALSE) -> 2974 | Q766: =VLOOKUP(orders[[#This Row],[EmployeeID]],employee_territory[],2,FALSE) -> 6897 | R766: =VLOOKUP(orders[[#This Row],[Territory]],territories[],4,FALSE) -> Eastern | S766: =VLOOKUP(orders[[#This Row],[ShipVia]],shippers[],2,FALSE) -> Federal Shipping | T766: =YEAR(orders[[#This Row],[OrderDate]]) -> 1998 | U766: =MONTH(orders[[#This Row],[OrderDate]]) -> 4
A767: 11013 | B767: ROMEY | C767: 2 | D767: 35894 | E767: 35922 | F767: 35895 | G767: 1 | H767: 32.99 | I767: Romero y tomillo | J767: Gran Va, 1 | K767: Madrid | L767: NULL | M767: 28001 | N767: Spain | O767: =VLOOKUP(orders[[#This Row],[OrderID]],Table15[],4,FALSE) -> 36 | P767: =VLOOKUP(orders[[#This Row],[OrderID]],Table15[],2,FALSE) -> 361 | Q767: =VLOOKUP(orders[[#This Row],[EmployeeID]],employee_territory[],2,FALSE) -> 1581 | R767: =VLOOKUP(orders[[#This Row],[Territory]],territories[],4,FALSE) -> Eastern | S767: =VLOOKUP(orders[[#This Row],[ShipVia]],shippers[],2,FALSE) -> Speedy Express | T767: =YEAR(orders[[#This Row],[OrderDate]]) -> 1998 | U767: =MONTH(orders[[#This Row],[OrderDate]]) -> 4
A768: 11014 | B768: LINOD | C768: 2 | D768: 35895 | E768: 35923 | F768: 35900 | G768: 3 | H768: 23.6 | I768: LINO-Delicateses | J768: Ave. 5 de Mayo Porlamar | K768: I. de Margarita | L768: Nueva Esparta | M768: 4980 | N768: Venezuela | O768: =VLOOKUP(orders[[#This Row],[OrderID]],Table15[],4,FALSE) -> 28 | P768: =VLOOKUP(orders[[#This Row],[OrderID]],Table15[],2,FALSE) -> 270.2 | Q768: =VLOOKUP(orders[[#This Row],[EmployeeID]],employee_territory[],2,FALSE) -> 1581 | R768: =VLOOKUP(orders[[#This Row],[Territory]],territories[],4,FALSE) -> Eastern | S768: =VLOOKUP(orders[[#This Row],[ShipVia]],shippers[],2,FALSE) -> Federal Shipping | T768: =YEAR(orders[[#This Row],[OrderDate]]) -> 1998 | U768: =MONTH(orders[[#This Row],[OrderDate]]) -> 4
A769: 11015 | B769: SANTG | C769: 2 | D769: 35895 | E769: 35909 | F769: 35905 | G769: 2 | H769: 4.62 | I769: Sant Gourmet | J769: Erling Skakkes gate 78 | K769: Stavern | L769: NULL | M769: 4110 | N769: Norway | O769: =VLOOKUP(orders[[#This Row],[OrderID]],Table15[],4,FALSE) -> 33 | P769: =VLOOKUP(orders[[#This Row],[OrderID]],Table15[],2,FALSE) -> 622.35 | Q769: =VLOOKUP(orders[[#This Row],[EmployeeID]],employee_territory[],2,FALSE) -> 1581 | R769: =VLOOKUP(orders[[#This Row],[Territory]],territories[],4,FALSE) -> Eastern | S769: =VLOOKUP(orders[[#This Row],[ShipVia]],shippers[],2,FALSE) -> United Package | T769: =YEAR(orders[[#This Row],[OrderDate]]) -> 1998 | U769: =MONTH(orders[[#This Row],[OrderDate]]) -> 4
A770: 11016 | B770: AROUT | C770: 9 | D770: 35895 | E770: 35923 | F770: 35898 | G770: 2 | H770: 33.8 | I770: Around the Horn | J770: Brook Farm Stratford St. Mary | K770: Colchester | L770: Essex | M770: CO7 6JX | N770: UK | O770: =VLOOKUP(orders[[#This Row],[OrderID]],Table15[],4,FALSE) -> 31 | P770: =VLOOKUP(orders[[#This Row],[OrderID]],Table15[],2,FALSE) -> 491.5 | Q770: =VLOOKUP(orders[[#This Row],[EmployeeID]],employee_territory[],2,FALSE) -> 3049 | R770: =VLOOKUP(orders[[#This Row],[Territory]],territories[],4,FALSE) -> Northern | S770: =VLOOKUP(orders[[#This Row],[ShipVia]],shippers[],2,FALSE) -> United Package | T770: =YEAR(orders[[#This Row],[OrderDate]]) -> 1998 | U770: =MONTH(orders[[#This Row],[OrderDate]]) -> 4
A771: 11017 | B771: ERNSH | C771: 9 | D771: 35898 | E771: 35926 | F771: 35905 | G771: 2 | H771: 754.26 | I771: Ernst Handel | J771: Kirchgasse 6 | K771: Graz | L771: NULL | M771: 8010 | N771: Austria | O771: =VLOOKUP(orders[[#This Row],[OrderID]],Table15[],4,FALSE) -> 165 | P771: =VLOOKUP(orders[[#This Row],[OrderID]],Table15[],2,FALSE) -> 6750 | Q771: =VLOOKUP(orders[[#This Row],[EmployeeID]],employee_territory[],2,FALSE) -> 3049 | R771: =VLOOKUP(orders[[#This Row],[Territory]],territories[],4,FALSE) -> Northern | S771: =VLOOKUP(orders[[#This Row],[ShipVia]],shippers[],2,FALSE) -> United Package | T771: =YEAR(orders[[#This Row],[OrderDate]]) -> 1998 | U771: =MONTH(orders[[#This Row],[OrderDate]]) -> 4
A772: 11018 | B772: LONEP | C772: 4 | D772: 35898 | E772: 35926 | F772: 35901 | G772: 2 | H772: 11.65 | I772: Lonesome Pine Restaurant | J772: 89 Chiaroscuro Rd. | K772: Portland | L772: OR | M772: 97219 | N772: USA | O772: =VLOOKUP(orders[[#This Row],[OrderID]],Table15[],4,FALSE) -> 35 | P772: =VLOOKUP(orders[[#This Row],[OrderID]],Table15[],2,FALSE) -> 1575 | Q772: =VLOOKUP(orders[[#This Row],[EmployeeID]],employee_territory[],2,FALSE) -> 20852 | R772: =VLOOKUP(orders[[#This Row],[Territory]],territories[],4,FALSE) -> Eastern | S772: =VLOOKUP(orders[[#This Row],[ShipVia]],shippers[],2,FALSE) -> United Package | T772: =YEAR(orders[[#This Row],[OrderDate]]) -> 1998 | U772: =MONTH(orders[[#This Row],[OrderDate]]) -> 4
A773: 11019 | B773: RANCH | C773: 6 | D773: 35898 | E773: 35926 | G773: 3 | H773: 3.17 | I773: Rancho grande | J773: Av. del Libertador 900 | K773: Buenos Aires | L773: NULL | M773: 1010 | N773: Argentina | O773: =VLOOKUP(orders[[#This Row],[OrderID]],Table15[],4,FALSE) -> 5 | P773: =VLOOKUP(orders[[#This Row],[OrderID]],Table15[],2,FALSE) -> 76 | Q773: =VLOOKUP(orders[[#This Row],[EmployeeID]],employee_territory[],2,FALSE) -> 85014 | R773: =VLOOKUP(orders[[#This Row],[Territory]],territories[],4,FALSE) -> Westerns | S773: =VLOOKUP(orders[[#This Row],[ShipVia]],shippers[],2,FALSE) -> Federal Shipping | T773: =YEAR(orders[[#This Row],[OrderDate]]) -> 1998 | U773: =MONTH(orders[[#This Row],[OrderDate]]) -> 4
A774: 11020 | B774: OTTIK | C774: 2 | D774: 35899 | E774: 35927 | F774: 35901 | G774: 2 | H774: 43.3 | I774: Ottilies Kseladen | J774: Mehrheimerstr. 369 | K774: Kln | L774: NULL | M774: 50739 | N774: Germany | O774: =VLOOKUP(orders[[#This Row],[OrderID]],Table15[],4,FALSE) -> 24 | P774: =VLOOKUP(orders[[#This Row],[OrderID]],Table15[],2,FALSE) -> 744 | Q774: =VLOOKUP(orders[[#This Row],[EmployeeID]],employee_territory[],2,FALSE) -> 1581 | R774: =VLOOKUP(orders[[#This Row],[Territory]],territories[],4,FALSE) -> Eastern | S774: =VLOOKUP(orders[[#This Row],[ShipVia]],shippers[],2,FALSE) -> United Package | T774: =YEAR(orders[[#This Row],[OrderDate]]) -> 1998 | U774: =MONTH(orders[[#This Row],[OrderDate]]) -> 4
A775: 11021 | B775: QUICK | C775: 3 | D775: 35899 | E775: 35927 | F775: 35906 | G775: 1 | H775: 297.18 | I775: QUICK-Stop | J775: Taucherstrae 10 | K775: Cunewalde | L775: NULL | M775: 1307 | N775: Germany | O775: =VLOOKUP(orders[[#This Row],[OrderID]],Table15[],4,FALSE) -> 168 | P775: =VLOOKUP(orders[[#This Row],[OrderID]],Table15[],2,FALSE) -> 6941.49 | Q775: =VLOOKUP(orders[[#This Row],[EmployeeID]],employee_territory[],2,FALSE) -> 30346 | R775: =VLOOKUP(orders[[#This Row],[Territory]],territories[],4,FALSE) -> Southern | S775: =VLOOKUP(orders[[#This Row],[ShipVia]],shippers[],2,FALSE) -> Speedy Express | T775: =YEAR(orders[[#This Row],[OrderDate]]) -> 1998 | U775: =MONTH(orders[[#This Row],[OrderDate]]) -> 4
A776: 11022 | B776: HANAR | C776: 9 | D776: 35899 | E776: 35927 | F776: 35919 | G776: 2 | H776: 6.27 | I776: Hanari Carnes | J776: Rua do Pao, 67 | K776: Rio de Janeiro | L776: RJ | M776: 05454-876 | N776: Brazil | O776: =VLOOKUP(orders[[#This Row],[OrderID]],Table15[],4,FALSE) -> 65 | P776: =VLOOKUP(orders[[#This Row],[OrderID]],Table15[],2,FALSE) -> 1402 | Q776: =VLOOKUP(orders[[#This Row],[EmployeeID]],employee_territory[],2,FALSE) -> 3049 | R776: =VLOOKUP(orders[[#This Row],[Territory]],territories[],4,FALSE) -> Northern | S776: =VLOOKUP(orders[[#This Row],[ShipVia]],shippers[],2,FALSE) -> United Package | T776: =YEAR(orders[[#This Row],[OrderDate]]) -> 1998 | U776: =MONTH(orders[[#This Row],[OrderDate]]) -> 4
A777: 11023 | B777: BSBEV | C777: 1 | D777: 35899 | E777: 35913 | F777: 35909 | G777: 2 | H777: 123.83 | I777: B-s Beverages | J777: Fauntleroy Circus | K777: London | L777: NULL | M777: EC2 5NT | N777: UK | O777: =VLOOKUP(orders[[#This Row],[OrderID]],Table15[],4,FALSE) -> 34 | P777: =VLOOKUP(orders[[#This Row],[OrderID]],Table15[],2,FALSE) -> 1500 | Q777: =VLOOKUP(orders[[#This Row],[EmployeeID]],employee_territory[],2,FALSE) -> 6897 | R777: =VLOOKUP(orders[[#This Row],[Territory]],territories[],4,FALSE) -> Eastern | S777: =VLOOKUP(orders[[#This Row],[ShipVia]],shippers[],2,FALSE) -> United Package | T777: =YEAR(orders[[#This Row],[OrderDate]]) -> 1998 | U777: =MONTH(orders[[#This Row],[OrderDate]]) -> 4
A778: 11024 | B778: EASTC | C778: 4 | D778: 35900 | E778: 35928 | F778: 35905 | G778: 1 | H778: 74.36 | I778: Eastern Connection | J778: 35 King George | K778: London | L778: NULL | M778: WX3 6FW | N778: UK | O778: =VLOOKUP(orders[[#This Row],[OrderID]],Table15[],4,FALSE) -> 113 | P778: =VLOOKUP(orders[[#This Row],[OrderID]],Table15[],2,FALSE) -> 1966.81 | Q778: =VLOOKUP(orders[[#This Row],[EmployeeID]],employee_territory[],2,FALSE) -> 20852 | R778: =VLOOKUP(orders[[#This Row],[Territory]],territories[],4,FALSE) -> Eastern | S778: =VLOOKUP(orders[[#This Row],[ShipVia]],shippers[],2,FALSE) -> Speedy Express | T778: =YEAR(orders[[#This Row],[OrderDate]]) -> 1998 | U778: =MONTH(orders[[#This Row],[OrderDate]]) -> 4
A779: 11025 | B779: WARTH | C779: 6 | D779: 35900 | E779: 35928 | F779: 35909 | G779: 3 | H779: 29.17 | I779: Wartian Herkku | J779: Torikatu 38 | K779: Oulu | L779: NULL | M779: 90110 | N779: Finland | O779: =VLOOKUP(orders[[#This Row],[OrderID]],Table15[],4,FALSE) -> 30 | P779: =VLOOKUP(orders[[#This Row],[OrderID]],Table15[],2,FALSE) -> 300 | Q779: =VLOOKUP(orders[[#This Row],[EmployeeID]],employee_territory[],2,FALSE) -> 85014 | R779: =VLOOKUP(orders[[#This Row],[Territory]],territories[],4,FALSE) -> Westerns | S779: =VLOOKUP(orders[[#This Row],[ShipVia]],shippers[],2,FALSE) -> Federal Shipping | T779: =YEAR(orders[[#This Row],[OrderDate]]) -> 1998 | U779: =MONTH(orders[[#This Row],[OrderDate]]) -> 4
A780: 11026 | B780: FRANS | C780: 4 | D780: 35900 | E780: 35928 | F780: 35913 | G780: 1 | H780: 47.09 | I780: Franchi S.p.A. | J780: Via Monte Bianco 34 | K780: Torino | L780: NULL | M780: 10100 | N780: Italy | O780: =VLOOKUP(orders[[#This Row],[OrderID]],Table15[],4,FALSE) -> 18 | P780: =VLOOKUP(orders[[#This Row],[OrderID]],Table15[],2,FALSE) -> 1030 | Q780: =VLOOKUP(orders[[#This Row],[EmployeeID]],employee_territory[],2,FALSE) -> 20852 | R780: =VLOOKUP(orders[[#This Row],[Territory]],territories[],4,FALSE) -> Eastern | S780: =VLOOKUP(orders[[#This Row],[ShipVia]],shippers[],2,FALSE) -> Speedy Express | T780: =YEAR(orders[[#This Row],[OrderDate]]) -> 1998 | U780: =MONTH(orders[[#This Row],[OrderDate]]) -> 4
A781: 11027 | B781: BOTTM | C781: 1 | D781: 35901 | E781: 35929 | F781: 35905 | G781: 1 | H781: 52.52 | I781: Bottom-Dollar Markets | J781: 23 Tsawassen Blvd. | K781: Tsawassen | L781: BC | M781: T2F 8M4 | N781: Canada | O781: =VLOOKUP(orders[[#This Row],[OrderID]],Table15[],4,FALSE) -> 51 | P781: =VLOOKUP(orders[[#This Row],[OrderID]],Table15[],2,FALSE) -> 1170.3 | Q781: =VLOOKUP(orders[[#This Row],[EmployeeID]],employee_territory[],2,FALSE) -> 6897 | R781: =VLOOKUP(orders[[#This Row],[Territory]],territories[],4,FALSE) -> Eastern | S781: =VLOOKUP(orders[[#This Row],[ShipVia]],shippers[],2,FALSE) -> Speedy Express | T781: =YEAR(orders[[#This Row],[OrderDate]]) -> 1998 | U781: =MONTH(orders[[#This Row],[OrderDate]]) -> 4
A782: 11028 | B782: KOENE | C782: 2 | D782: 35901 | E782: 35929 | F782: 35907 | G782: 1 | H782: 29.59 | I782: Kniglich Essen | J782: Maubelstr. 90 | K782: Brandenburg | L782: NULL | M782: 14776 | N782: Germany | O782: =VLOOKUP(orders[[#This Row],[OrderID]],Table15[],4,FALSE) -> 59 | P782: =VLOOKUP(orders[[#This Row],[OrderID]],Table15[],2,FALSE) -> 2160 | Q782: =VLOOKUP(orders[[#This Row],[EmployeeID]],employee_territory[],2,FALSE) -> 1581 | R782: =VLOOKUP(orders[[#This Row],[Territory]],territories[],4,FALSE) -> Eastern | S782: =VLOOKUP(orders[[#This Row],[ShipVia]],shippers[],2,FALSE) -> Speedy Express | T782: =YEAR(orders[[#This Row],[OrderDate]]) -> 1998 | U782: =MONTH(orders[[#This Row],[OrderDate]]) -> 4
A783: 11029 | B783: CHOPS | C783: 4 | D783: 35901 | E783: 35929 | F783: 35912 | G783: 1 | H783: 47.84 | I783: Chop-suey Chinese | J783: Hauptstr. 31 | K783: Bern | L783: NULL | M783: 3012 | N783: Switzerland | O783: =VLOOKUP(orders[[#This Row],[OrderID]],Table15[],4,FALSE) -> 32 | P783: =VLOOKUP(orders[[#This Row],[OrderID]],Table15[],2,FALSE) -> 1286.8 | Q783: =VLOOKUP(orders[[#This Row],[EmployeeID]],employee_territory[],2,FALSE) -> 20852 | R783: =VLOOKUP(orders[[#This Row],[Territory]],territories[],4,FALSE) -> Eastern | S783: =VLOOKUP(orders[[#This Row],[ShipVia]],shippers[],2,FALSE) -> Speedy Express | T783: =YEAR(orders[[#This Row],[OrderDate]]) -> 1998 | U783: =MONTH(orders[[#This Row],[OrderDate]]) -> 4
A784: 11030 | B784: SAVEA | C784: 7 | D784: 35902 | E784: 35930 | F784: 35912 | G784: 2 | H784: 830.75 | I784: Save-a-lot Markets | J784: 187 Suffolk Ln. | K784: Boise | L784: ID | M784: 83720 | N784: USA | O784: =VLOOKUP(orders[[#This Row],[OrderID]],Table15[],4,FALSE) -> 330 | P784: =VLOOKUP(orders[[#This Row],[OrderID]],Table15[],2,FALSE) -> 16321.9 | Q784: =VLOOKUP(orders[[#This Row],[EmployeeID]],employee_territory[],2,FALSE) -> 60179 | R784: =VLOOKUP(orders[[#This Row],[Territory]],territories[],4,FALSE) -> Westerns | S784: =VLOOKUP(orders[[#This Row],[ShipVia]],shippers[],2,FALSE) -> United Package | T784: =YEAR(orders[[#This Row],[OrderDate]]) -> 1998 | U784: =MONTH(orders[[#This Row],[OrderDate]]) -> 4
A785: 11031 | B785: SAVEA | C785: 6 | D785: 35902 | E785: 35930 | F785: 35909 | G785: 2 | H785: 227.22 | I785: Save-a-lot Markets | J785: 187 Suffolk Ln. | K785: Boise | L785: ID | M785: 83720 | N785: USA | O785: =VLOOKUP(orders[[#This Row],[OrderID]],Table15[],4,FALSE) -> 182 | P785: =VLOOKUP(orders[[#This Row],[OrderID]],Table15[],2,FALSE) -> 2393.5 | Q785: =VLOOKUP(orders[[#This Row],[EmployeeID]],employee_territory[],2,FALSE) -> 85014 | R785: =VLOOKUP(orders[[#This Row],[Territory]],territories[],4,FALSE) -> Westerns | S785: =VLOOKUP(orders[[#This Row],[ShipVia]],shippers[],2,FALSE) -> United Package | T785: =YEAR(orders[[#This Row],[OrderDate]]) -> 1998 | U785: =MONTH(orders[[#This Row],[OrderDate]]) -> 4
... A792: 11038 | B792: SUPRD | C792: 1 | D792: 35906 | E792: 35934 | F792: 35915 | G792: 2 | H792: 29.59 | I792: Suprmes dlices | J792: Boulevard Tirou, 255 | K792: Charleroi | L792: NULL | M792: B-6000 | N792: Belgium | O792: =VLOOKUP(orders[[#This Row],[OrderID]],Table15[],4,FALSE) -> 37 | P792: =VLOOKUP(orders[[#This Row],[OrderID]],Table15[],2,FALSE) -> 751 | Q792: =VLOOKUP(orders[[#This Row],[EmployeeID]],employee_territory[],2,FALSE) -> 6897 | R792: =VLOOKUP(orders[[#This Row],[Territory]],territories[],4,FALSE) -> Eastern | S792: =VLOOKUP(orders[[#This Row],[ShipVia]],shippers[],2,FALSE) -> United Package | T792: =YEAR(orders[[#This Row],[OrderDate]]) -> 1998 | U792: =MONTH(orders[[#This Row],[OrderDate]]) -> 4
A793: 11039 | B793: LINOD | C793: 1 | D793: 35906 | E793: 35934 | G793: 2 | H793: 65 | I793: LINO-Delicateses | J793: Ave. 5 de Mayo Porlamar | K793: I. de Margarita | L793: Nueva Esparta | M793: 4980 | N793: Venezuela | O793: =VLOOKUP(orders[[#This Row],[OrderID]],Table15[],4,FALSE) -> 132 | P793: =VLOOKUP(orders[[#This Row],[OrderID]],Table15[],2,FALSE) -> 3090 | Q793: =VLOOKUP(orders[[#This Row],[EmployeeID]],employee_territory[],2,FALSE) -> 6897 | R793: =VLOOKUP(orders[[#This Row],[Territory]],territories[],4,FALSE) -> Eastern | S793: =VLOOKUP(orders[[#This Row],[ShipVia]],shippers[],2,FALSE) -> United Package | T793: =YEAR(orders[[#This Row],[OrderDate]]) -> 1998 | U793: =MONTH(orders[[#This Row],[OrderDate]]) -> 4
A794: 11040 | B794: GREAL | C794: 4 | D794: 35907 | E794: 35935 | G794: 3 | H794: 18.84 | I794: Great Lakes Food Market | J794: 2732 Baker Blvd. | K794: Eugene | L794: OR | M794: 97403 | N794: USA | O794: =VLOOKUP(orders[[#This Row],[OrderID]],Table15[],4,FALSE) -> 20 | P794: =VLOOKUP(orders[[#This Row],[OrderID]],Table15[],2,FALSE) -> 200 | Q794: =VLOOKUP(orders[[#This Row],[EmployeeID]],employee_territory[],2,FALSE) -> 20852 | R794: =VLOOKUP(orders[[#This Row],[Territory]],territories[],4,FALSE) -> Eastern | S794: =VLOOKUP(orders[[#This Row],[ShipVia]],shippers[],2,FALSE) -> Federal Shipping | T794: =YEAR(orders[[#This Row],[OrderDate]]) -> 1998 | U794: =MONTH(orders[[#This Row],[OrderDate]]) -> 4
A795: 11041 | B795: CHOPS | C795: 3 | D795: 35907 | E795: 35935 | F795: 35913 | G795: 2 | H795: 48.22 | I795: Chop-suey Chinese | J795: Hauptstr. 31 | K795: Bern | L795: NULL | M795: 3012 | N795: Switzerland | O795: =VLOOKUP(orders[[#This Row],[OrderID]],Table15[],4,FALSE) -> 60 | P795: =VLOOKUP(orders[[#This Row],[OrderID]],Table15[],2,FALSE) -> 1887 | Q795: =VLOOKUP(orders[[#This Row],[EmployeeID]],employee_territory[],2,FALSE) -> 30346 | R795: =VLOOKUP(orders[[#This Row],[Territory]],territories[],4,FALSE) -> Southern | S795: =VLOOKUP(orders[[#This Row],[ShipVia]],shippers[],2,FALSE) -> United Package | T795: =YEAR(orders[[#This Row],[OrderDate]]) -> 1998 | U795: =MONTH(orders[[#This Row],[OrderDate]]) -> 4
A796: 11042 | B796: COMMI | C796: 2 | D796: 35907 | E796: 35921 | F796: 35916 | G796: 1 | H796: 29.99 | I796: Comrcio Mineiro | J796: Av. dos Lusadas, 23 | K796: Sao Paulo | L796: SP | M796: 05432-043 | N796: Brazil | O796: =VLOOKUP(orders[[#This Row],[OrderID]],Table15[],4,FALSE) -> 19 | P796: =VLOOKUP(orders[[#This Row],[OrderID]],Table15[],2,FALSE) -> 405.75 | Q796: =VLOOKUP(orders[[#This Row],[EmployeeID]],employee_territory[],2,FALSE) -> 1581 | R796: =VLOOKUP(orders[[#This Row],[Territory]],territories[],4,FALSE) -> Eastern | S796: =VLOOKUP(orders[[#This Row],[ShipVia]],shippers[],2,FALSE) -> Speedy Express | T796: =YEAR(orders[[#This Row],[OrderDate]]) -> 1998 | U796: =MONTH(orders[[#This Row],[OrderDate]]) -> 4
A797: 11043 | B797: SPECD | C797: 5 | D797: 35907 | E797: 35935 | F797: 35914 | G797: 2 | H797: 8.8 | I797: Spcialits du monde | J797: 25, rue Lauriston | K797: Paris | L797: NULL | M797: 75016 | N797: France | O797: =VLOOKUP(orders[[#This Row],[OrderID]],Table15[],4,FALSE) -> 10 | P797: =VLOOKUP(orders[[#This Row],[OrderID]],Table15[],2,FALSE) -> 210 | Q797: =VLOOKUP(orders[[#This Row],[EmployeeID]],employee_territory[],2,FALSE) -> 2903 | R797: =VLOOKUP(orders[[#This Row],[Territory]],territories[],4,FALSE) -> Eastern | S797: =VLOOKUP(orders[[#This Row],[ShipVia]],shippers[],2,FALSE) -> United Package | T797: =YEAR(orders[[#This Row],[OrderDate]]) -> 1998 | U797: =MONTH(orders[[#This Row],[OrderDate]]) -> 4
A798: 11044 | B798: WOLZA | C798: 4 | D798: 35908 | E798: 35936 | F798: 35916 | G798: 1 | H798: 8.72 | I798: Wolski Zajazd | J798: ul. Filtrowa 68 | K798: Warszawa | L798: NULL | M798: 01-012 | N798: Poland | O798: =VLOOKUP(orders[[#This Row],[OrderID]],Table15[],4,FALSE) -> 12 | P798: =VLOOKUP(orders[[#This Row],[OrderID]],Table15[],2,FALSE) -> 591.6 | Q798: =VLOOKUP(orders[[#This Row],[EmployeeID]],employee_territory[],2,FALSE) -> 20852 | R798: =VLOOKUP(orders[[#This Row],[Territory]],territories[],4,FALSE) -> Eastern | S798: =VLOOKUP(orders[[#This Row],[ShipVia]],shippers[],2,FALSE) -> Speedy Express | T798: =YEAR(orders[[#This Row],[OrderDate]]) -> 1998 | U798: =MONTH(orders[[#This Row],[OrderDate]]) -> 4
A799: 11045 | B799: BOTTM | C799: 6 | D799: 35908 | E799: 35936 | G799: 2 | H799: 70.58 | I799: Bottom-Dollar Markets | J799: 23 Tsawassen Blvd. | K799: Tsawassen | L799: BC | M799: T2F 8M4 | N799: Canada | O799: =VLOOKUP(orders[[#This Row],[OrderID]],Table15[],4,FALSE) -> 39 | P799: =VLOOKUP(orders[[#This Row],[OrderID]],Table15[],2,FALSE) -> 1309.5 | Q799: =VLOOKUP(orders[[#This Row],[EmployeeID]],employee_territory[],2,FALSE) -> 85014 | R799: =VLOOKUP(orders[[#This Row],[Territory]],territories[],4,FALSE) -> Westerns | S799: =VLOOKUP(orders[[#This Row],[ShipVia]],shippers[],2,FALSE) -> United Package | T799: =YEAR(orders[[#This Row],[OrderDate]]) -> 1998 | U799: =MONTH(orders[[#This Row],[OrderDate]]) -> 4
A800: 11046 | B800: WANDK | C800: 8 | D800: 35908 | E800: 35936 | F800: 35909 | G800: 2 | H800: 71.64 | I800: Die Wandernde Kuh | J800: Adenauerallee 900 | K800: Stuttgart | L800: NULL | M800: 70563 | N800: Germany | O800: =VLOOKUP(orders[[#This Row],[OrderID]],Table15[],4,FALSE) -> 53 | P800: =VLOOKUP(orders[[#This Row],[OrderID]],Table15[],2,FALSE) -> 1564 | Q800: =VLOOKUP(orders[[#This Row],[EmployeeID]],employee_territory[],2,FALSE) -> 19428 | R800: =VLOOKUP(orders[[#This Row],[Territory]],territories[],4,FALSE) -> Northern | S800: =VLOOKUP(orders[[#This Row],[ShipVia]],shippers[],2,FALSE) -> United Package | T800: =YEAR(orders[[#This Row],[OrderDate]]) -> 1998 | U800: =MONTH(orders[[#This Row],[OrderDate]]) -> 4
A801: 11047 | B801: EASTC | C801: 7 | D801: 35909 | E801: 35937 | F801: 35916 | G801: 3 | H801: 46.62 | I801: Eastern Connection | J801: 35 King George | K801: London | L801: NULL | M801: WX3 6FW | N801: UK | O801: =VLOOKUP(orders[[#This Row],[OrderID]],Table15[],4,FALSE) -> 55 | P801: =VLOOKUP(orders[[#This Row],[OrderID]],Table15[],2,FALSE) -> 1090.5 | Q801: =VLOOKUP(orders[[#This Row],[EmployeeID]],employee_territory[],2,FALSE) -> 60179 | R801: =VLOOKUP(orders[[#This Row],[Territory]],territories[],4,FALSE) -> Westerns | S801: =VLOOKUP(orders[[#This Row],[ShipVia]],shippers[],2,FALSE) -> Federal Shipping | T801: =YEAR(orders[[#This Row],[OrderDate]]) -> 1998 | U801: =MONTH(orders[[#This Row],[OrderDate]]) -> 4
A802: 11048 | B802: BOTTM | C802: 7 | D802: 35909 | E802: 35937 | F802: 35915 | G802: 3 | H802: 24.12 | I802: Bottom-Dollar Markets | J802: 23 Tsawassen Blvd. | K802: Tsawassen | L802: BC | M802: T2F 8M4 | N802: Canada | O802: =VLOOKUP(orders[[#This Row],[OrderID]],Table15[],4,FALSE) -> 42 | P802: =VLOOKUP(orders[[#This Row],[OrderID]],Table15[],2,FALSE) -> 525 | Q802: =VLOOKUP(orders[[#This Row],[EmployeeID]],employee_territory[],2,FALSE) -> 60179 | R802: =VLOOKUP(orders[[#This Row],[Territory]],territories[],4,FALSE) -> Westerns | S802: =VLOOKUP(orders[[#This Row],[ShipVia]],shippers[],2,FALSE) -> Federal Shipping | T802: =YEAR(orders[[#This Row],[OrderDate]]) -> 1998 | U802: =MONTH(orders[[#This Row],[OrderDate]]) -> 4
A803: 11049 | B803: GOURL | C803: 3 | D803: 35909 | E803: 35937 | F803: 35919 | G803: 1 | H803: 8.34 | I803: Gourmet Lanchonetes | J803: Av. Brasil, 442 | K803: Campinas | L803: SP | M803: 04876-786 | N803: Brazil | O803: =VLOOKUP(orders[[#This Row],[OrderID]],Table15[],4,FALSE) -> 14 | P803: =VLOOKUP(orders[[#This Row],[OrderID]],Table15[],2,FALSE) -> 342 | Q803: =VLOOKUP(orders[[#This Row],[EmployeeID]],employee_territory[],2,FALSE) -> 30346 | R803: =VLOOKUP(orders[[#This Row],[Territory]],territories[],4,FALSE) -> Southern | S803: =VLOOKUP(orders[[#This Row],[ShipVia]],shippers[],2,FALSE) -> Speedy Express | T803: =YEAR(orders[[#This Row],[OrderDate]]) -> 1998 | U803: =MONTH(orders[[#This Row],[OrderDate]]) -> 4
A804: 11050 | B804: FOLKO | C804: 8 | D804: 35912 | E804: 35940 | F804: 35920 | G804: 2 | H804: 59.41 | I804: Folk och f HB | J804: kergatan 24 | K804: Brcke | L804: NULL | M804: S-844 67 | N804: Sweden | O804: =VLOOKUP(orders[[#This Row],[OrderID]],Table15[],4,FALSE) -> 50 | P804: =VLOOKUP(orders[[#This Row],[OrderID]],Table15[],2,FALSE) -> 900 | Q804: =VLOOKUP(orders[[#This Row],[EmployeeID]],employee_territory[],2,FALSE) -> 19428 | R804: =VLOOKUP(orders[[#This Row],[Territory]],territories[],4,FALSE) -> Northern | S804: =VLOOKUP(orders[[#This Row],[ShipVia]],shippers[],2,FALSE) -> United Package | T804: =YEAR(orders[[#This Row],[OrderDate]]) -> 1998 | U804: =MONTH(orders[[#This Row],[OrderDate]]) -> 4
A805: 11051 | B805: LAMAI | C805: 7 | D805: 35912 | E805: 35940 | G805: 3 | H805: 2.79 | I805: La maison d-Asie | J805: 1 rue Alsace-Lorraine | K805: Toulouse | L805: NULL | M805: 31000 | N805: France | O805: =VLOOKUP(orders[[#This Row],[OrderID]],Table15[],4,FALSE) -> 10 | P805: =VLOOKUP(orders[[#This Row],[OrderID]],Table15[],2,FALSE) -> 45 | Q805: =VLOOKUP(orders[[#This Row],[EmployeeID]],employee_territory[],2,FALSE) -> 60179 | R805: =VLOOKUP(orders[[#This Row],[Territory]],territories[],4,FALSE) -> Westerns | S805: =VLOOKUP(orders[[#This Row],[ShipVia]],shippers[],2,FALSE) -> Federal Shipping | T805: =YEAR(orders[[#This Row],[OrderDate]]) -> 1998 | U805: =MONTH(orders[[#This Row],[OrderDate]]) -> 4
A806: 11052 | B806: HANAR | C806: 3 | D806: 35912 | E806: 35940 | F806: 35916 | G806: 1 | H806: 67.26 | I806: Hanari Carnes | J806: Rua do Pao, 67 | K806: Rio de Janeiro | L806: RJ | M806: 05454-876 | N806: Brazil | O806: =VLOOKUP(orders[[#This Row],[OrderID]],Table15[],4,FALSE) -> 40 | P806: =VLOOKUP(orders[[#This Row],[OrderID]],Table15[],2,FALSE) -> 1665 | Q806: =VLOOKUP(orders[[#This Row],[EmployeeID]],employee_territory[],2,FALSE) -> 30346 | R806: =VLOOKUP(orders[[#This Row],[Territory]],territories[],4,FALSE) -> Southern | S806: =VLOOKUP(orders[[#This Row],[ShipVia]],shippers[],2,FALSE) -> Speedy Express | T806: =YEAR(orders[[#This Row],[OrderDate]]) -> 1998 | U806: =MONTH(orders[[#This Row],[OrderDate]]) -> 4
A807: 11053 | B807: PICCO | C807: 2 | D807: 35912 | E807: 35940 | F807: 35914 | G807: 2 | H807: 53.05 | I807: Piccolo und mehr | J807: Geislweg 14 | K807: Salzburg | L807: NULL | M807: 5020 | N807: Austria | O807: =VLOOKUP(orders[[#This Row],[OrderID]],Table15[],4,FALSE) -> 80 | P807: =VLOOKUP(orders[[#This Row],[OrderID]],Table15[],2,FALSE) -> 3658.75 | Q807: =VLOOKUP(orders[[#This Row],[EmployeeID]],employee_territory[],2,FALSE) -> 1581 | R807: =VLOOKUP(orders[[#This Row],[Territory]],territories[],4,FALSE) -> Eastern | S807: =VLOOKUP(orders[[#This Row],[ShipVia]],shippers[],2,FALSE) -> United Package | T807: =YEAR(orders[[#This Row],[OrderDate]]) -> 1998 | U807: =MONTH(orders[[#This Row],[OrderDate]]) -> 4
A808: 11054 | B808: CACTU | C808: 8 | D808: 35913 | E808: 35941 | G808: 1 | H808: 0.33 | I808: Cactus Comidas para llevar | J808: Cerrito 333 | K808: Buenos Aires | L808: NULL | M808: 1010 | N808: Argentina | O808: =VLOOKUP(orders[[#This Row],[OrderID]],Table15[],4,FALSE) -> 30 | P808: =VLOOKUP(orders[[#This Row],[OrderID]],Table15[],2,FALSE) -> 305 | Q808: =VLOOKUP(orders[[#This Row],[EmployeeID]],employee_territory[],2,FALSE) -> 19428 | R808: =VLOOKUP(orders[[#This Row],[Territory]],territories[],4,FALSE) -> Northern | S808: =VLOOKUP(orders[[#This Row],[ShipVia]],shippers[],2,FALSE) -> Speedy Express | T808: =YEAR(orders[[#This Row],[OrderDate]]) -> 1998 | U808: =MONTH(orders[[#This Row],[OrderDate]]) -> 4
A809: 11055 | B809: HILAA | C809: 7 | D809: 35913 | E809: 35941 | F809: 35920 | G809: 2 | H809: 120.92 | I809: HILARION-Abastos | J809: Carrera 22 con Ave. Carlos Soublette #8-35 | K809: San Cristbal | L809: Tchira | M809: 5022 | N809: Venezuela | O809: =VLOOKUP(orders[[#This Row],[OrderID]],Table15[],4,FALSE) -> 70 | P809: =VLOOKUP(orders[[#This Row],[OrderID]],Table15[],2,FALSE) -> 1727.5 | Q809: =VLOOKUP(orders[[#This Row],[EmployeeID]],employee_territory[],2,FALSE) -> 60179 | R809: =VLOOKUP(orders[[#This Row],[Territory]],territories[],4,FALSE) -> Westerns | S809: =VLOOKUP(orders[[#This Row],[ShipVia]],shippers[],2,FALSE) -> United Package | T809: =YEAR(orders[[#This Row],[OrderDate]]) -> 1998 | U809: =MONTH(orders[[#This Row],[OrderDate]]) -> 4
A810: 11056 | B810: EASTC | C810: 8 | D810: 35913 | E810: 35927 | F810: 35916 | G810: 2 | H810: 278.96 | I810: Eastern Connection | J810: 35 King George | K810: London | L810: NULL | M810: WX3 6FW | N810: UK | O810: =VLOOKUP(orders[[#This Row],[OrderID]],Table15[],4,FALSE) -> 125 | P810: =VLOOKUP(orders[[#This Row],[OrderID]],Table15[],2,FALSE) -> 3740 | Q810: =VLOOKUP(orders[[#This Row],[EmployeeID]],employee_territory[],2,FALSE) -> 19428 | R810: =VLOOKUP(orders[[#This Row],[Territory]],territories[],4,FALSE) -> Northern | S810: =VLOOKUP(orders[[#This Row],[ShipVia]],shippers[],2,FALSE) -> United Package | T810: =YEAR(orders[[#This Row],[OrderDate]]) -> 1998 | U810: =MONTH(orders[[#This Row],[OrderDate]]) -> 4
A811: 11057 | B811: NORTS | C811: 3 | D811: 35914 | E811: 35942 | F811: 35916 | G811: 3 | H811: 4.13 | I811: North/South | J811: South House 300 Queensbridge | K811: London | L811: NULL | M811: SW7 1RZ | N811: UK | O811: =VLOOKUP(orders[[#This Row],[OrderID]],Table15[],4,FALSE) -> 3 | P811: =VLOOKUP(orders[[#This Row],[OrderID]],Table15[],2,FALSE) -> 45 | Q811: =VLOOKUP(orders[[#This Row],[EmployeeID]],employee_territory[],2,FALSE) -> 30346 | R811: =VLOOKUP(orders[[#This Row],[Territory]],territories[],4,FALSE) -> Southern | S811: =VLOOKUP(orders[[#This Row],[ShipVia]],shippers[],2,FALSE) -> Federal Shipping | T811: =YEAR(orders[[#This Row],[OrderDate]]) -> 1998 | U811: =MONTH(orders[[#This Row],[OrderDate]]) -> 4
A812: 11058 | B812: BLAUS | C812: 9 | D812: 35914 | E812: 35942 | G812: 3 | H812: 31.14 | I812: Blauer See Delikatessen | J812: Forsterstr. 57 | K812: Mannheim | L812: NULL | M812: 68306 | N812: Germany | O812: =VLOOKUP(orders[[#This Row],[OrderID]],Table15[],4,FALSE) -> 28 | P812: =VLOOKUP(orders[[#This Row],[OrderID]],Table15[],2,FALSE) -> 858 | Q812: =VLOOKUP(orders[[#This Row],[EmployeeID]],employee_territory[],2,FALSE) -> 3049 | R812: =VLOOKUP(orders[[#This Row],[Territory]],territories[],4,FALSE) -> Northern | S812: =VLOOKUP(orders[[#This Row],[ShipVia]],shippers[],2,FALSE) -> Federal Shipping | T812: =YEAR(orders[[#This Row],[OrderDate]]) -> 1998 | U812: =MONTH(orders[[#This Row],[OrderDate]]) -> 4
A813: 11059 | B813: RICAR | C813: 2 | D813: 35914 | E813: 35956 | G813: 2 | H813: 85.8 | I813: Ricardo Adocicados | J813: Av. Copacabana, 267 | K813: Rio de Janeiro | L813: RJ | M813: 02389-890 | N813: Brazil | O813: =VLOOKUP(orders[[#This Row],[OrderID]],Table15[],4,FALSE) -> 77 | P813: =VLOOKUP(orders[[#This Row],[OrderID]],Table15[],2,FALSE) -> 1838 | Q813: =VLOOKUP(orders[[#This Row],[EmployeeID]],employee_territory[],2,FALSE) -> 1581 | R813: =VLOOKUP(orders[[#This Row],[Territory]],territories[],4,FALSE) -> Eastern | S813: =VLOOKUP(orders[[#This Row],[ShipVia]],shippers[],2,FALSE) -> United Package | T813: =YEAR(orders[[#This Row],[OrderDate]]) -> 1998 | U813: =MONTH(orders[[#This Row],[OrderDate]]) -> 4
A814: 11060 | B814: FRANS | C814: 2 | D814: 35915 | E814: 35943 | F814: 35919 | G814: 2 | H814: 10.98 | I814: Franchi S.p.A. | J814: Via Monte Bianco 34 | K814: Torino | L814: NULL | M814: 10100 | N814: Italy | O814: =VLOOKUP(orders[[#This Row],[OrderID]],Table15[],4,FALSE) -> 14 | P814: =VLOOKUP(orders[[#This Row],[OrderID]],Table15[],2,FALSE) -> 266 | Q814: =VLOOKUP(orders[[#This Row],[EmployeeID]],employee_territory[],2,FALSE) -> 1581 | R814: =VLOOKUP(orders[[#This Row],[Territory]],territories[],4,FALSE) -> Eastern | S814: =VLOOKUP(orders[[#This Row],[ShipVia]],shippers[],2,FALSE) -> United Package | T814: =YEAR(orders[[#This Row],[OrderDate]]) -> 1998 | U814: =MONTH(orders[[#This Row],[OrderDate]]) -> 4
A815: 11061 | B815: GREAL | C815: 4 | D815: 35915 | E815: 35957 | G815: 3 | H815: 14.01 | I815: Great Lakes Food Market | J815: 2732 Baker Blvd. | K815: Eugene | L815: OR | M815: 97403 | N815: USA | O815: =VLOOKUP(orders[[#This Row],[OrderID]],Table15[],4,FALSE) -> 15 | P815: =VLOOKUP(orders[[#This Row],[OrderID]],Table15[],2,FALSE) -> 510 | Q815: =VLOOKUP(orders[[#This Row],[EmployeeID]],employee_territory[],2,FALSE) -> 20852 | R815: =VLOOKUP(orders[[#This Row],[Territory]],territories[],4,FALSE) -> Eastern | S815: =VLOOKUP(orders[[#This Row],[ShipVia]],shippers[],2,FALSE) -> Federal Shipping | T815: =YEAR(orders[[#This Row],[OrderDate]]) -> 1998 | U815: =MONTH(orders[[#This Row],[OrderDate]]) -> 4
A816: 11062 | B816: REGGC | C816: 4 | D816: 35915 | E816: 35943 | G816: 2 | H816: 29.93 | I816: Reggiani Caseifici | J816: Strada Provinciale 124 | K816: Reggio Emilia | L816: NULL | M816: 42100 | N816: Italy | O816: =VLOOKUP(orders[[#This Row],[OrderID]],Table15[],4,FALSE) -> 22 | P816: =VLOOKUP(orders[[#This Row],[OrderID]],Table15[],2,FALSE) -> 508 | Q816: =VLOOKUP(orders[[#This Row],[EmployeeID]],employee_territory[],2,FALSE) -> 20852 | R816: =VLOOKUP(orders[[#This Row],[Territory]],territories[],4,FALSE) -> Eastern | S816: =VLOOKUP(orders[[#This Row],[ShipVia]],shippers[],2,FALSE) -> United Package | T816: =YEAR(orders[[#This Row],[OrderDate]]) -> 1998 | U816: =MONTH(orders[[#This Row],[OrderDate]]) -> 4
A817: 11063 | B817: HUNGO | C817: 3 | D817: 35915 | E817: 35943 | F817: 35921 | G817: 2 | H817: 81.73 | I817: Hungry Owl All-Night Grocers | J817: 8 Johnstown Road | K817: Cork | L817: Co. Cork | M817: NULL | N817: Ireland | O817: =VLOOKUP(orders[[#This Row],[OrderID]],Table15[],4,FALSE) -> 100 | P817: =VLOOKUP(orders[[#This Row],[OrderID]],Table15[],2,FALSE) -> 1445.5 | Q817: =VLOOKUP(orders[[#This Row],[EmployeeID]],employee_territory[],2,FALSE) -> 30346 | R817: =VLOOKUP(orders[[#This Row],[Territory]],territories[],4,FALSE) -> Southern | S817: =VLOOKUP(orders[[#This Row],[ShipVia]],shippers[],2,FALSE) -> United Package | T817: =YEAR(orders[[#This Row],[OrderDate]]) -> 1998 | U817: =MONTH(orders[[#This Row],[OrderDate]]) -> 4
A818: 11064 | B818: SAVEA | C818: 1 | D818: 35916 | E818: 35944 | F818: 35919 | G818: 1 | H818: 30.09 | I818: Save-a-lot Markets | J818: 187 Suffolk Ln. | K818: Boise | L818: ID | M818: 83720 | N818: USA | O818: =VLOOKUP(orders[[#This Row],[OrderID]],Table15[],4,FALSE) -> 173 | P818: =VLOOKUP(orders[[#This Row],[OrderID]],Table15[],2,FALSE) -> 4722.3 | Q818: =VLOOKUP(orders[[#This Row],[EmployeeID]],employee_territory[],2,FALSE) -> 6897 | R818: =VLOOKUP(orders[[#This Row],[Territory]],territories[],4,FALSE) -> Eastern | S818: =VLOOKUP(orders[[#This Row],[ShipVia]],shippers[],2,FALSE) -> Speedy Express | T818: =YEAR(orders[[#This Row],[OrderDate]]) -> 1998 | U818: =MONTH(orders[[#This Row],[OrderDate]]) -> 5
A819: 11065 | B819: LILAS | C819: 8 | D819: 35916 | E819: 35944 | G819: 1 | H819: 12.91 | I819: LILA-Supermercado | J819: Carrera 52 con Ave. Bolvar #65-98 Llano Largo | K819: Barquisimeto | L819: Lara | M819: 3508 | N819: Venezuela | O819: =VLOOKUP(orders[[#This Row],[OrderID]],Table15[],4,FALSE) -> 24 | P819: =VLOOKUP(orders[[#This Row],[OrderID]],Table15[],2,FALSE) -> 252.56 | Q819: =VLOOKUP(orders[[#This Row],[EmployeeID]],employee_territory[],2,FALSE) -> 19428 | R819: =VLOOKUP(orders[[#This Row],[Territory]],territories[],4,FALSE) -> Northern | S819: =VLOOKUP(orders[[#This Row],[ShipVia]],shippers[],2,FALSE) -> Speedy Express | T819: =YEAR(orders[[#This Row],[OrderDate]]) -> 1998 | U819: =MONTH(orders[[#This Row],[OrderDate]]) -> 5
A820: 11066 | B820: WHITC | C820: 7 | D820: 35916 | E820: 35944 | F820: 35919 | G820: 2 | H820: 44.72 | I820: White Clover Markets | J820: 1029 - 12th Ave. S. | K820: Seattle | L820: WA | M820: 98124 | N820: USA | O820: =VLOOKUP(orders[[#This Row],[OrderID]],Table15[],4,FALSE) -> 80 | P820: =VLOOKUP(orders[[#This Row],[OrderID]],Table15[],2,FALSE) -> 928.75 | Q820: =VLOOKUP(orders[[#This Row],[EmployeeID]],employee_territory[],2,FALSE) -> 60179 | R820: =VLOOKUP(orders[[#This Row],[Territory]],territories[],4,FALSE) -> Westerns | S820: =VLOOKUP(orders[[#This Row],[ShipVia]],shippers[],2,FALSE) -> United Package | T820: =YEAR(orders[[#This Row],[OrderDate]]) -> 1998 | U820: =MONTH(orders[[#This Row],[OrderDate]]) -> 5
A821: 11067 | B821: DRACD | C821: 1 | D821: 35919 | E821: 35933 | F821: 35921 | G821: 2 | H821: 7.98 | I821: Drachenblut Delikatessen | J821: Walserweg 21 | K821: Aachen | L821: NULL | M821: 52066 | N821: Germany | O821: =VLOOKUP(orders[[#This Row],[OrderID]],Table15[],4,FALSE) -> 9 | P821: =VLOOKUP(orders[[#This Row],[OrderID]],Table15[],2,FALSE) -> 86.85 | Q821: =VLOOKUP(orders[[#This Row],[EmployeeID]],employee_territory[],2,FALSE) -> 6897 | R821: =VLOOKUP(orders[[#This Row],[Territory]],territories[],4,FALSE) -> Eastern | S821: =VLOOKUP(orders[[#This Row],[ShipVia]],shippers[],2,FALSE) -> United Package | T821: =YEAR(orders[[#This Row],[OrderDate]]) -> 1998 | U821: =MONTH(orders[[#This Row],[OrderDate]]) -> 5
A822: 11068 | B822: QUEEN | C822: 8 | D822: 35919 | E822: 35947 | G822: 2 | H822: 81.75 | I822: Queen Cozinha | J822: Alameda dos Canrios, 891 | K822: Sao Paulo | L822: SP | M822: 05487-020 | N822: Brazil | O822: =VLOOKUP(orders[[#This Row],[OrderID]],Table15[],4,FALSE) -> 72 | P822: =VLOOKUP(orders[[#This Row],[OrderID]],Table15[],2,FALSE) -> 2384.8 | Q822: =VLOOKUP(orders[[#This Row],[EmployeeID]],employee_territory[],2,FALSE) -> 19428 | R822: =VLOOKUP(orders[[#This Row],[Territory]],territories[],4,FALSE) -> Northern | S822: =VLOOKUP(orders[[#This Row],[ShipVia]],shippers[],2,FALSE) -> United Package | T822: =YEAR(orders[[#This Row],[OrderDate]]) -> 1998 | U822: =MONTH(orders[[#This Row],[OrderDate]]) -> 5
A823: 11069 | B823: TORTU | C823: 1 | D823: 35919 | E823: 35947 | F823: 35921 | G823: 2 | H823: 15.67 | I823: Tortuga Restaurante | J823: Avda. Azteca 123 | K823: Mxico D.F. | L823: NULL | M823: 5033 | N823: Mexico | O823: =VLOOKUP(orders[[#This Row],[OrderID]],Table15[],4,FALSE) -> 20 | P823: =VLOOKUP(orders[[#This Row],[OrderID]],Table15[],2,FALSE) -> 360 | Q823: =VLOOKUP(orders[[#This Row],[EmployeeID]],employee_territory[],2,FALSE) -> 6897 | R823: =VLOOKUP(orders[[#This Row],[Territory]],territories[],4,FALSE) -> Eastern | S823: =VLOOKUP(orders[[#This Row],[ShipVia]],shippers[],2,FALSE) -> United Package | T823: =YEAR(orders[[#This Row],[OrderDate]]) -> 1998 | U823: =MONTH(orders[[#This Row],[OrderDate]]) -> 5
A824: 11070 | B824: LEHMS | C824: 2 | D824: 35920 | E824: 35948 | G824: 1 | H824: 136 | I824: Lehmanns Marktstand | J824: Magazinweg 7 | K824: Frankfurt a.M. | L824: NULL | M824: 60528 | N824: Germany | O824: =VLOOKUP(orders[[#This Row],[OrderID]],Table15[],4,FALSE) -> 110 | P824: =VLOOKUP(orders[[#This Row],[OrderID]],Table15[],2,FALSE) -> 1873.5 | Q824: =VLOOKUP(orders[[#This Row],[EmployeeID]],employee_territory[],2,FALSE) -> 1581 | R824: =VLOOKUP(orders[[#This Row],[Territory]],territories[],4,FALSE) -> Eastern | S824: =VLOOKUP(orders[[#This Row],[ShipVia]],shippers[],2,FALSE) -> Speedy Express | T824: =YEAR(orders[[#This Row],[OrderDate]]) -> 1998 | U824: =MONTH(orders[[#This Row],[OrderDate]]) -> 5
A825: 11071 | B825: LILAS | C825: 1 | D825: 35920 | E825: 35948 | G825: 1 | H825: 0.93 | I825: LILA-Supermercado | J825: Carrera 52 con Ave. Bolvar #65-98 Llano Largo | K825: Barquisimeto | L825: Lara | M825: 3508 | N825: Venezuela | O825: =VLOOKUP(orders[[#This Row],[OrderID]],Table15[],4,FALSE) -> 25 | P825: =VLOOKUP(orders[[#This Row],[OrderID]],Table15[],2,FALSE) -> 510 | Q825: =VLOOKUP(orders[[#This Row],[EmployeeID]],employee_territory[],2,FALSE) -> 6897 | R825: =VLOOKUP(orders[[#This Row],[Territory]],territories[],4,FALSE) -> Eastern | S825: =VLOOKUP(orders[[#This Row],[ShipVia]],shippers[],2,FALSE) -> Speedy Express | T825: =YEAR(orders[[#This Row],[OrderDate]]) -> 1998 | U825: =MONTH(orders[[#This Row],[OrderDate]]) -> 5
A826: 11072 | B826: ERNSH | C826: 4 | D826: 35920 | E826: 35948 | G826: 2 | H826: 258.64 | I826: Ernst Handel | J826: Kirchgasse 6 | K826: Graz | L826: NULL | M826: 8010 | N826: Austria | O826: =VLOOKUP(orders[[#This Row],[OrderID]],Table15[],4,FALSE) -> 200 | P826: =VLOOKUP(orders[[#This Row],[OrderID]],Table15[],2,FALSE) -> 5218 | Q826: =VLOOKUP(orders[[#This Row],[EmployeeID]],employee_territory[],2,FALSE) -> 20852 | R826: =VLOOKUP(orders[[#This Row],[Territory]],territories[],4,FALSE) -> Eastern | S826: =VLOOKUP(orders[[#This Row],[ShipVia]],shippers[],2,FALSE) -> United Package | T826: =YEAR(orders[[#This Row],[OrderDate]]) -> 1998 | U826: =MONTH(orders[[#This Row],[OrderDate]]) -> 5
A827: 11073 | B827: PERIC | C827: 2 | D827: 35920 | E827: 35948 | G827: 2 | H827: 24.95 | I827: Pericles Comidas clsicas | J827: Calle Dr. Jorge Cash 321 | K827: Mxico D.F. | L827: NULL | M827: 5033 | N827: Mexico | O827: =VLOOKUP(orders[[#This Row],[OrderID]],Table15[],4,FALSE) -> 30 | P827: =VLOOKUP(orders[[#This Row],[OrderID]],Table15[],2,FALSE) -> 300 | Q827: =VLOOKUP(orders[[#This Row],[EmployeeID]],employee_territory[],2,FALSE) -> 1581 | R827: =VLOOKUP(orders[[#This Row],[Territory]],territories[],4,FALSE) -> Eastern | S827: =VLOOKUP(orders[[#This Row],[ShipVia]],shippers[],2,FALSE) -> United Package | T827: =YEAR(orders[[#This Row],[OrderDate]]) -> 1998 | U827: =MONTH(orders[[#This Row],[OrderDate]]) -> 5
A828: 11074 | B828: SIMOB | C828: 7 | D828: 35921 | E828: 35949 | G828: 2 | H828: 18.44 | I828: Simons bistro | J828: Vinbltet 34 | K828: Kobenhavn | L828: NULL | M828: 1734 | N828: Denmark | O828: =VLOOKUP(orders[[#This Row],[OrderID]],Table15[],4,FALSE) -> 14 | P828: =VLOOKUP(orders[[#This Row],[OrderID]],Table15[],2,FALSE) -> 244.3 | Q828: =VLOOKUP(orders[[#This Row],[EmployeeID]],employee_territory[],2,FALSE) -> 60179 | R828: =VLOOKUP(orders[[#This Row],[Territory]],territories[],4,FALSE) -> Westerns | S828: =VLOOKUP(orders[[#This Row],[ShipVia]],shippers[],2,FALSE) -> United Package | T828: =YEAR(orders[[#This Row],[OrderDate]]) -> 1998 | U828: =MONTH(orders[[#This Row],[OrderDate]]) -> 5
A829: 11075 | B829: RICSU | C829: 8 | D829: 35921 | E829: 35949 | G829: 2 | H829: 6.19 | I829: Richter Supermarkt | J829: Starenweg 5 | K829: Genve | L829: NULL | M829: 1204 | N829: Switzerland | O829: =VLOOKUP(orders[[#This Row],[OrderID]],Table15[],4,FALSE) -> 42 | P829: =VLOOKUP(orders[[#This Row],[OrderID]],Table15[],2,FALSE) -> 586 | Q829: =VLOOKUP(orders[[#This Row],[EmployeeID]],employee_territory[],2,FALSE) -> 19428 | R829: =VLOOKUP(orders[[#This Row],[Territory]],territories[],4,FALSE) -> Northern | S829: =VLOOKUP(orders[[#This Row],[ShipVia]],shippers[],2,FALSE) -> United Package | T829: =YEAR(orders[[#This Row],[OrderDate]]) -> 1998 | U829: =MONTH(orders[[#This Row],[OrderDate]]) -> 5
A830: 11076 | B830: BONAP | C830: 4 | D830: 35921 | E830: 35949 | G830: 2 | H830: 38.28 | I830: Bon app- | J830: 12, rue des Bouchers | K830: Marseille | L830: NULL | M830: 13008 | N830: France | O830: =VLOOKUP(orders[[#This Row],[OrderID]],Table15[],4,FALSE) -> 50 | P830: =VLOOKUP(orders[[#This Row],[OrderID]],Table15[],2,FALSE) -> 1057 | Q830: =VLOOKUP(orders[[#This Row],[EmployeeID]],employee_territory[],2,FALSE) -> 20852 | R830: =VLOOKUP(orders[[#This Row],[Territory]],territories[],4,FALSE) -> Eastern | S830: =VLOOKUP(orders[[#This Row],[ShipVia]],shippers[],2,FALSE) -> United Package | T830: =YEAR(orders[[#This Row],[OrderDate]]) -> 1998 | U830: =MONTH(orders[[#This Row],[OrderDate]]) -> 5
A831: 11077 | B831: RATTC | C831: 1 | D831: 35921 | E831: 35949 | G831: 2 | H831: 8.53 | I831: Rattlesnake Canyon Grocery | J831: 2817 Milton Dr. | K831: Albuquerque | L831: NM | M831: 87110 | N831: USA | O831: =VLOOKUP(orders[[#This Row],[OrderID]],Table15[],4,FALSE) -> 72 | P831: =VLOOKUP(orders[[#This Row],[OrderID]],Table15[],2,FALSE) -> 1374.6 | Q831: =VLOOKUP(orders[[#This Row],[EmployeeID]],employee_territory[],2,FALSE) -> 6897 | R831: =VLOOKUP(orders[[#This Row],[Territory]],territories[],4,FALSE) -> Eastern | S831: =VLOOKUP(orders[[#This Row],[ShipVia]],shippers[],2,FALSE) -> United Package | T831: =YEAR(orders[[#This Row],[OrderDate]]) -> 1998 | U831: =MONTH(orders[[#This Row],[OrderDate]]) -> 5

Sheet Dashboard2
AR23: `

Sheet Dashboard

Sheet order_details (2)
A1: OrderID | B1: ProductID | C1: UnitPrice | D1: Quantity | E1: Discount | F1: Line Sale | G1: SupplierID | H1: Year | I1: ProductName | J1: SupplierName | K1: ShipCountry | L1: ShipVia | M1: ShipperName | N1: CustomerID | O1: Region | P1: CategoryID | Q1: CategoryName | R1: Month
A2: 10248 | B2: 11 | C2: 14 | D2: 12 | E2: 0 | F2: =order_details__2[[#This Row],[UnitPrice]]*order_details__2[[#This Row],[Quantity]] -> 168 | G2: =VLOOKUP(order_details__2[[#This Row],[ProductID]],products[],3,FALSE) -> 5 | H2: =VLOOKUP(order_details__2[[#This Row],[OrderID]],orders[],20,FALSE) -> 1996 | I2: =VLOOKUP(order_details__2[[#This Row],[ProductID]],products[],2,FALSE) -> Queso Cabrales | J2: =VLOOKUP(order_details__2[[#This Row],[SupplierID]],suppliers[],2,FALSE) -> Cooperativa de Quesos 'Las Cabras' | K2: =VLOOKUP(order_details__2[[#This Row],[OrderID]],orders[],14,FALSE) -> France | L2: =VLOOKUP(order_details__2[[#This Row],[OrderID]],orders[],7,FALSE) -> 3 | M2: =VLOOKUP(order_details__2[[#This Row],[ShipVia ]],shippers[],2,FALSE) -> Federal Shipping | N2: =VLOOKUP(order_details__2[[#This Row],[OrderID]],orders[],2,FALSE) -> VINET | O2: =VLOOKUP(order_details__2[[#This Row],[OrderID]],orders[],18,FALSE) -> Eastern | P2: =VLOOKUP(order_details__2[[#This Row],[ProductID]],products[],4,FALSE) -> 4 | Q2: =VLOOKUP(order_details__2[[#This Row],[CategoryID]],categories[],2,FALSE) -> Dairy Products | R2: =VLOOKUP(order_details__2[[#This Row],[OrderID]],orders[],21,FALSE) -> 7
A3: 10248 | B3: 42 | C3: 9.8 | D3: 10 | E3: 0 | F3: =order_details__2[[#This Row],[UnitPrice]]*order_details__2[[#This Row],[Quantity]] -> 98 | G3: =VLOOKUP(order_details__2[[#This Row],[ProductID]],products[],3,FALSE) -> 20 | H3: =VLOOKUP(order_details__2[[#This Row],[OrderID]],orders[],20,FALSE) -> 1996 | I3: =VLOOKUP(order_details__2[[#This Row],[ProductID]],products[],2,FALSE) -> Singaporean Hokkien Fried Mee | J3: =VLOOKUP(order_details__2[[#This Row],[SupplierID]],suppliers[],2,FALSE) -> Leka Trading | K3: =VLOOKUP(order_details__2[[#This Row],[OrderID]],orders[],14,FALSE) -> France | L3: =VLOOKUP(order_details__2[[#This Row],[OrderID]],orders[],7,FALSE) -> 3 | M3: =VLOOKUP(order_details__2[[#This Row],[ShipVia ]],shippers[],2,FALSE) -> Federal Shipping | N3: =VLOOKUP(order_details__2[[#This Row],[OrderID]],orders[],2,FALSE) -> VINET | O3: =VLOOKUP(order_details__2[[#This Row],[OrderID]],orders[],18,FALSE) -> Eastern | P3: =VLOOKUP(order_details__2[[#This Row],[ProductID]],products[],4,FALSE) -> 5 | Q3: =VLOOKUP(order_details__2[[#This Row],[CategoryID]],categories[],2,FALSE) -> Grains/Cereals | R3: =VLOOKUP(order_details__2[[#This Row],[OrderID]],orders[],21,FALSE) -> 7
A4: 10248 | B4: 72 | C4: 34.8 | D4: 5 | E4: 0 | F4: =order_details__2[[#This Row],[UnitPrice]]*order_details__2[[#This Row],[Quantity]] -> 174 | G4: =VLOOKUP(order_details__2[[#This Row],[ProductID]],products[],3,FALSE) -> 14 | H4: =VLOOKUP(order_details__2[[#This Row],[OrderID]],orders[],20,FALSE) -> 1996 | I4: =VLOOKUP(order_details__2[[#This Row],[ProductID]],products[],2,FALSE) -> Mozzarella di Giovanni | J4: =VLOOKUP(order_details__2[[#This Row],[SupplierID]],suppliers[],2,FALSE) -> Formaggi Fortini s.r.l. | K4: =VLOOKUP(order_details__2[[#This Row],[OrderID]],orders[],14,FALSE) -> France | L4: =VLOOKUP(order_details__2[[#This Row],[OrderID]],orders[],7,FALSE) -> 3 | M4: =VLOOKUP(order_details__2[[#This Row],[ShipVia ]],shippers[],2,FALSE) -> Federal Shipping | N4: =VLOOKUP(order_details__2[[#This Row],[OrderID]],orders[],2,FALSE) -> VINET | O4: =VLOOKUP(order_details__2[[#This Row],[OrderID]],orders[],18,FALSE) -> Eastern | P4: =VLOOKUP(order_details__2[[#This Row],[ProductID]],products[],4,FALSE) -> 4 | Q4: =VLOOKUP(order_details__2[[#This Row],[CategoryID]],categories[],2,FALSE) -> Dairy Products | R4: =VLOOKUP(order_details__2[[#This Row],[OrderID]],orders[],21,FALSE) -> 7
A5: 10249 | B5: 14 | C5: 18.6 | D5: 9 | E5: 0 | F5: =order_details__2[[#This Row],[UnitPrice]]*order_details__2[[#This Row],[Quantity]] -> 167.4 | G5: =VLOOKUP(order_details__2[[#This Row],[ProductID]],products[],3,FALSE) -> 6 | H5: =VLOOKUP(order_details__2[[#This Row],[OrderID]],orders[],20,FALSE) -> 1996 | I5: =VLOOKUP(order_details__2[[#This Row],[ProductID]],products[],2,FALSE) -> Tofu | J5: =VLOOKUP(order_details__2[[#This Row],[SupplierID]],suppliers[],2,FALSE) -> Mayumi's | K5: =VLOOKUP(order_details__2[[#This Row],[OrderID]],orders[],14,FALSE) -> Germany | L5: =VLOOKUP(order_details__2[[#This Row],[OrderID]],orders[],7,FALSE) -> 1 | M5: =VLOOKUP(order_details__2[[#This Row],[ShipVia ]],shippers[],2,FALSE) -> Speedy Express | N5: =VLOOKUP(order_details__2[[#This Row],[OrderID]],orders[],2,FALSE) -> TOMSP | O5: =VLOOKUP(order_details__2[[#This Row],[OrderID]],orders[],18,FALSE) -> Westerns | P5: =VLOOKUP(order_details__2[[#This Row],[ProductID]],products[],4,FALSE) -> 7 | Q5: =VLOOKUP(order_details__2[[#This Row],[CategoryID]],categories[],2,FALSE) -> Produce | R5: =VLOOKUP(order_details__2[[#This Row],[OrderID]],orders[],21,FALSE) -> 7
A6: 10249 | B6: 51 | C6: 42.4 | D6: 40 | E6: 0 | F6: =order_details__2[[#This Row],[UnitPrice]]*order_details__2[[#This Row],[Quantity]] -> 1696 | G6: =VLOOKUP(order_details__2[[#This Row],[ProductID]],products[],3,FALSE) -> 24 | H6: =VLOOKUP(order_details__2[[#This Row],[OrderID]],orders[],20,FALSE) -> 1996 | I6: =VLOOKUP(order_details__2[[#This Row],[ProductID]],products[],2,FALSE) -> Manjimup Dried Apples | J6: =VLOOKUP(order_details__2[[#This Row],[SupplierID]],suppliers[],2,FALSE) -> G'day, Mate | K6: =VLOOKUP(order_details__2[[#This Row],[OrderID]],orders[],14,FALSE) -> Germany | L6: =VLOOKUP(order_details__2[[#This Row],[OrderID]],orders[],7,FALSE) -> 1 | M6: =VLOOKUP(order_details__2[[#This Row],[ShipVia ]],shippers[],2,FALSE) -> Speedy Express | N6: =VLOOKUP(order_details__2[[#This Row],[OrderID]],orders[],2,FALSE) -> TOMSP | O6: =VLOOKUP(order_details__2[[#This Row],[OrderID]],orders[],18,FALSE) -> Westerns | P6: =VLOOKUP(order_details__2[[#This Row],[ProductID]],products[],4,FALSE) -> 7 | Q6: =VLOOKUP(order_details__2[[#This Row],[CategoryID]],categories[],2,FALSE) -> Produce | R6: =VLOOKUP(order_details__2[[#This Row],[OrderID]],orders[],21,FALSE) -> 7
A7: 10250 | B7: 41 | C7: 7.7 | D7: 10 | E7: 0 | F7: =order_details__2[[#This Row],[UnitPrice]]*order_details__2[[#This Row],[Quantity]] -> 77 | G7: =VLOOKUP(order_details__2[[#This Row],[ProductID]],products[],3,FALSE) -> 19 | H7: =VLOOKUP(order_details__2[[#This Row],[OrderID]],orders[],20,FALSE) -> 1996 | I7: =VLOOKUP(order_details__2[[#This Row],[ProductID]],products[],2,FALSE) -> Jack's New England Clam Chowder | J7: =VLOOKUP(order_details__2[[#This Row],[SupplierID]],suppliers[],2,FALSE) -> New England Seafood Cannery | K7: =VLOOKUP(order_details__2[[#This Row],[OrderID]],orders[],14,FALSE) -> Brazil | L7: =VLOOKUP(order_details__2[[#This Row],[OrderID]],orders[],7,FALSE) -> 2 | M7: =VLOOKUP(order_details__2[[#This Row],[ShipVia ]],shippers[],2,FALSE) -> United Package | N7: =VLOOKUP(order_details__2[[#This Row],[OrderID]],orders[],2,FALSE) -> HANAR | O7: =VLOOKUP(order_details__2[[#This Row],[OrderID]],orders[],18,FALSE) -> Eastern | P7: =VLOOKUP(order_details__2[[#This Row],[ProductID]],products[],4,FALSE) -> 8 | Q7: =VLOOKUP(order_details__2[[#This Row],[CategoryID]],categories[],2,FALSE) -> Seafood | R7: =VLOOKUP(order_details__2[[#This Row],[OrderID]],orders[],21,FALSE) -> 7
A8: 10250 | B8: 51 | C8: 42.4 | D8: 35 | E8: 0 | F8: =order_details__2[[#This Row],[UnitPrice]]*order_details__2[[#This Row],[Quantity]] -> 1484 | G8: =VLOOKUP(order_details__2[[#This Row],[ProductID]],products[],3,FALSE) -> 24 | H8: =VLOOKUP(order_details__2[[#This Row],[OrderID]],orders[],20,FALSE) -> 1996 | I8: =VLOOKUP(order_details__2[[#This Row],[ProductID]],products[],2,FALSE) -> Manjimup Dried Apples | J8: =VLOOKUP(order_details__2[[#This Row],[SupplierID]],suppliers[],2,FALSE) -> G'day, Mate | K8: =VLOOKUP(order_details__2[[#This Row],[OrderID]],orders[],14,FALSE) -> Brazil | L8: =VLOOKUP(order_details__2[[#This Row],[OrderID]],orders[],7,FALSE) -> 2 | M8: =VLOOKUP(order_details__2[[#This Row],[ShipVia ]],shippers[],2,FALSE) -> United Package | N8: =VLOOKUP(order_details__2[[#This Row],[OrderID]],orders[],2,FALSE) -> HANAR | O8: =VLOOKUP(order_details__2[[#This Row],[OrderID]],orders[],18,FALSE) -> Eastern | P8: =VLOOKUP(order_details__2[[#This Row],[ProductID]],products[],4,FALSE) -> 7 | Q8: =VLOOKUP(order_details__2[[#This Row],[CategoryID]],categories[],2,FALSE) -> Produce | R8: =VLOOKUP(order_details__2[[#This Row],[OrderID]],orders[],21,FALSE) -> 7
A9: 10250 | B9: 65 | C9: 16.8 | D9: 15 | E9: 0 | F9: =order_details__2[[#This Row],[UnitPrice]]*order_details__2[[#This Row],[Quantity]] -> 252 | G9: =VLOOKUP(order_details__2[[#This Row],[ProductID]],products[],3,FALSE) -> 2 | H9: =VLOOKUP(order_details__2[[#This Row],[OrderID]],orders[],20,FALSE) -> 1996 | I9: =VLOOKUP(order_details__2[[#This Row],[ProductID]],products[],2,FALSE) -> Louisiana Fiery Hot Pepper Sauce | J9: =VLOOKUP(order_details__2[[#This Row],[SupplierID]],suppliers[],2,FALSE) -> New Orleans Cajun Delights | K9: =VLOOKUP(order_details__2[[#This Row],[OrderID]],orders[],14,FALSE) -> Brazil | L9: =VLOOKUP(order_details__2[[#This Row],[OrderID]],orders[],7,FALSE) -> 2 | M9: =VLOOKUP(order_details__2[[#This Row],[ShipVia ]],shippers[],2,FALSE) -> United Package | N9: =VLOOKUP(order_details__2[[#This Row],[OrderID]],orders[],2,FALSE) -> HANAR | O9: =VLOOKUP(order_details__2[[#This Row],[OrderID]],orders[],18,FALSE) -> Eastern | P9: =VLOOKUP(order_details__2[[#This Row],[ProductID]],products[],4,FALSE) -> 2 | Q9: =VLOOKUP(order_details__2[[#This Row],[CategoryID]],categories[],2,FALSE) -> Condiments | R9: =VLOOKUP(order_details__2[[#This Row],[OrderID]],orders[],21,FALSE) -> 7
A10: 10251 | B10: 22 | C10: 16.8 | D10: 6 | E10: 0 | F10: =order_details__2[[#This Row],[UnitPrice]]*order_details__2[[#This Row],[Quantity]] -> 100.8 | G10: =VLOOKUP(order_details__2[[#This Row],[ProductID]],products[],3,FALSE) -> 9 | H10: =VLOOKUP(order_details__2[[#This Row],[OrderID]],orders[],20,FALSE) -> 1996 | I10: =VLOOKUP(order_details__2[[#This Row],[ProductID]],products[],2,FALSE) -> Gustaf's Knckebrd | J10: =VLOOKUP(order_details__2[[#This Row],[SupplierID]],suppliers[],2,FALSE) -> PB Knckebrd AB | K10: =VLOOKUP(order_details__2[[#This Row],[OrderID]],orders[],14,FALSE) -> France | L10: =VLOOKUP(order_details__2[[#This Row],[OrderID]],orders[],7,FALSE) -> 1 | M10: =VLOOKUP(order_details__2[[#This Row],[ShipVia ]],shippers[],2,FALSE) -> Speedy Express | N10: =VLOOKUP(order_details__2[[#This Row],[OrderID]],orders[],2,FALSE) -> VICTE | O10: =VLOOKUP(order_details__2[[#This Row],[OrderID]],orders[],18,FALSE) -> Southern | P10: =VLOOKUP(order_details__2[[#This Row],[ProductID]],products[],4,FALSE) -> 5 | Q10: =VLOOKUP(order_details__2[[#This Row],[CategoryID]],categories[],2,FALSE) -> Grains/Cereals | R10: =VLOOKUP(order_details__2[[#This Row],[OrderID]],orders[],21,FALSE) -> 7
A11: 10251 | B11: 57 | C11: 15.6 | D11: 15 | E11: 0 | F11: =order_details__2[[#This Row],[UnitPrice]]*order_details__2[[#This Row],[Quantity]] -> 234 | G11: =VLOOKUP(order_details__2[[#This Row],[ProductID]],products[],3,FALSE) -> 26 | H11: =VLOOKUP(order_details__2[[#This Row],[OrderID]],orders[],20,FALSE) -> 1996 | I11: =VLOOKUP(order_details__2[[#This Row],[ProductID]],products[],2,FALSE) -> Ravioli Angelo | J11: =VLOOKUP(order_details__2[[#This Row],[SupplierID]],suppliers[],2,FALSE) -> Pasta Buttini s.r.l. | K11: =VLOOKUP(order_details__2[[#This Row],[OrderID]],orders[],14,FALSE) -> France | L11: =VLOOKUP(order_details__2[[#This Row],[OrderID]],orders[],7,FALSE) -> 1 | M11: =VLOOKUP(order_details__2[[#This Row],[ShipVia ]],shippers[],2,FALSE) -> Speedy Express | N11: =VLOOKUP(order_details__2[[#This Row],[OrderID]],orders[],2,FALSE) -> VICTE | O11: =VLOOKUP(order_details__2[[#This Row],[OrderID]],orders[],18,FALSE) -> Southern | P11: =VLOOKUP(order_details__2[[#This Row],[ProductID]],products[],4,FALSE) -> 5 | Q11: =VLOOKUP(order_details__2[[#This Row],[CategoryID]],categories[],2,FALSE) -> Grains/Cereals | R11: =VLOOKUP(order_details__2[[#This Row],[OrderID]],orders[],21,FALSE) -> 7 | Y11: I have to create the 4 graphs again
A12: 10251 | B12: 65 | C12: 16.8 | D12: 20 | E12: 0 | F12: =order_details__2[[#This Row],[UnitPrice]]*order_details__2[[#This Row],[Quantity]] -> 336 | G12: =VLOOKUP(order_details__2[[#This Row],[ProductID]],products[],3,FALSE) -> 2 | H12: =VLOOKUP(order_details__2[[#This Row],[OrderID]],orders[],20,FALSE) -> 1996 | I12: =VLOOKUP(order_details__2[[#This Row],[ProductID]],products[],2,FALSE) -> Louisiana Fiery Hot Pepper Sauce | J12: =VLOOKUP(order_details__2[[#This Row],[SupplierID]],suppliers[],2,FALSE) -> New Orleans Cajun Delights | K12: =VLOOKUP(order_details__2[[#This Row],[OrderID]],orders[],14,FALSE) -> France | L12: =VLOOKUP(order_details__2[[#This Row],[OrderID]],orders[],7,FALSE) -> 1 | M12: =VLOOKUP(order_details__2[[#This Row],[ShipVia ]],shippers[],2,FALSE) -> Speedy Express | N12: =VLOOKUP(order_details__2[[#This Row],[OrderID]],orders[],2,FALSE) -> VICTE | O12: =VLOOKUP(order_details__2[[#This Row],[OrderID]],orders[],18,FALSE) -> Southern | P12: =VLOOKUP(order_details__2[[#This Row],[ProductID]],products[],4,FALSE) -> 2 | Q12: =VLOOKUP(order_details__2[[#This Row],[CategoryID]],categories[],2,FALSE) -> Condiments | R12: =VLOOKUP(order_details__2[[#This Row],[OrderID]],orders[],21,FALSE) -> 7 | Y12: since this would be enabling slicers
A13: 10252 | B13: 20 | C13: 64.8 | D13: 40 | E13: 0 | F13: =order_details__2[[#This Row],[UnitPrice]]*order_details__2[[#This Row],[Quantity]] -> 2592 | G13: =VLOOKUP(order_details__2[[#This Row],[ProductID]],products[],3,FALSE) -> 8 | H13: =VLOOKUP(order_details__2[[#This Row],[OrderID]],orders[],20,FALSE) -> 1996 | I13: =VLOOKUP(order_details__2[[#This Row],[ProductID]],products[],2,FALSE) -> Sir Rodney's Marmalade | J13: =VLOOKUP(order_details__2[[#This Row],[SupplierID]],suppliers[],2,FALSE) -> Specialty Biscuits, Ltd. | K13: =VLOOKUP(order_details__2[[#This Row],[OrderID]],orders[],14,FALSE) -> Belgium | L13: =VLOOKUP(order_details__2[[#This Row],[OrderID]],orders[],7,FALSE) -> 2 | M13: =VLOOKUP(order_details__2[[#This Row],[ShipVia ]],shippers[],2,FALSE) -> United Package | N13: =VLOOKUP(order_details__2[[#This Row],[OrderID]],orders[],2,FALSE) -> SUPRD | O13: =VLOOKUP(order_details__2[[#This Row],[OrderID]],orders[],18,FALSE) -> Eastern | P13: =VLOOKUP(order_details__2[[#This Row],[ProductID]],products[],4,FALSE) -> 3 | Q13: =VLOOKUP(order_details__2[[#This Row],[CategoryID]],categories[],2,FALSE) -> Confections | R13: =VLOOKUP(order_details__2[[#This Row],[OrderID]],orders[],21,FALSE) -> 7
A14: 10252 | B14: 33 | C14: 2 | D14: 25 | E14: 0 | F14: =order_details__2[[#This Row],[UnitPrice]]*order_details__2[[#This Row],[Quantity]] -> 50 | G14: =VLOOKUP(order_details__2[[#This Row],[ProductID]],products[],3,FALSE) -> 15 | H14: =VLOOKUP(order_details__2[[#This Row],[OrderID]],orders[],20,FALSE) -> 1996 | I14: =VLOOKUP(order_details__2[[#This Row],[ProductID]],products[],2,FALSE) -> Geitost | J14: =VLOOKUP(order_details__2[[#This Row],[SupplierID]],suppliers[],2,FALSE) -> Norske Meierier | K14: =VLOOKUP(order_details__2[[#This Row],[OrderID]],orders[],14,FALSE) -> Belgium | L14: =VLOOKUP(order_details__2[[#This Row],[OrderID]],orders[],7,FALSE) -> 2 | M14: =VLOOKUP(order_details__2[[#This Row],[ShipVia ]],shippers[],2,FALSE) -> United Package | N14: =VLOOKUP(order_details__2[[#This Row],[OrderID]],orders[],2,FALSE) -> SUPRD | O14: =VLOOKUP(order_details__2[[#This Row],[OrderID]],orders[],18,FALSE) -> Eastern | P14: =VLOOKUP(order_details__2[[#This Row],[ProductID]],products[],4,FALSE) -> 4 | Q14: =VLOOKUP(order_details__2[[#This Row],[CategoryID]],categories[],2,FALSE) -> Dairy Products | R14: =VLOOKUP(order_details__2[[#This Row],[OrderID]],orders[],21,FALSE) -> 7
A15: 10252 | B15: 60 | C15: 27.2 | D15: 40 | E15: 0 | F15: =order_details__2[[#This Row],[UnitPrice]]*order_details__2[[#This Row],[Quantity]] -> 1088 | G15: =VLOOKUP(order_details__2[[#This Row],[ProductID]],products[],3,FALSE) -> 28 | H15: =VLOOKUP(order_details__2[[#This Row],[OrderID]],orders[],20,FALSE) -> 1996 | I15: =VLOOKUP(order_details__2[[#This Row],[ProductID]],products[],2,FALSE) -> Camembert Pierrot | J15: =VLOOKUP(order_details__2[[#This Row],[SupplierID]],suppliers[],2,FALSE) -> Gai pturage | K15: =VLOOKUP(order_details__2[[#This Row],[OrderID]],orders[],14,FALSE) -> Belgium | L15: =VLOOKUP(order_details__2[[#This Row],[OrderID]],orders[],7,FALSE) -> 2 | M15: =VLOOKUP(order_details__2[[#This Row],[ShipVia ]],shippers[],2,FALSE) -> United Package | N15: =VLOOKUP(order_details__2[[#This Row],[OrderID]],orders[],2,FALSE) -> SUPRD | O15: =VLOOKUP(order_details__2[[#This Row],[OrderID]],orders[],18,FALSE) -> Eastern | P15: =VLOOKUP(order_details__2[[#This Row],[ProductID]],products[],4,FALSE) -> 4 | Q15: =VLOOKUP(order_details__2[[#This Row],[CategoryID]],categories[],2,FALSE) -> Dairy Products | R15: =VLOOKUP(order_details__2[[#This Row],[OrderID]],orders[],21,FALSE) -> 7
A16: 10253 | B16: 31 | C16: 10 | D16: 20 | E16: 0 | F16: =order_details__2[[#This Row],[UnitPrice]]*order_details__2[[#This Row],[Quantity]] -> 200 | G16: =VLOOKUP(order_details__2[[#This Row],[ProductID]],products[],3,FALSE) -> 14 | H16: =VLOOKUP(order_details__2[[#This Row],[OrderID]],orders[],20,FALSE) -> 1996 | I16: =VLOOKUP(order_details__2[[#This Row],[ProductID]],products[],2,FALSE) -> Gorgonzola Telino | J16: =VLOOKUP(order_details__2[[#This Row],[SupplierID]],suppliers[],2,FALSE) -> Formaggi Fortini s.r.l. | K16: =VLOOKUP(order_details__2[[#This Row],[OrderID]],orders[],14,FALSE) -> Brazil | L16: =VLOOKUP(order_details__2[[#This Row],[OrderID]],orders[],7,FALSE) -> 2 | M16: =VLOOKUP(order_details__2[[#This Row],[ShipVia ]],shippers[],2,FALSE) -> United Package | N16: =VLOOKUP(order_details__2[[#This Row],[OrderID]],orders[],2,FALSE) -> HANAR | O16: =VLOOKUP(order_details__2[[#This Row],[OrderID]],orders[],18,FALSE) -> Southern | P16: =VLOOKUP(order_details__2[[#This Row],[ProductID]],products[],4,FALSE) -> 4 | Q16: =VLOOKUP(order_details__2[[#This Row],[CategoryID]],categories[],2,FALSE) -> Dairy Products | R16: =VLOOKUP(order_details__2[[#This Row],[OrderID]],orders[],21,FALSE) -> 7
A17: 10253 | B17: 39 | C17: 14.4 | D17: 42 | E17: 0 | F17: =order_details__2[[#This Row],[UnitPrice]]*order_details__2[[#This Row],[Quantity]] -> 604.8 | G17: =VLOOKUP(order_details__2[[#This Row],[ProductID]],products[],3,FALSE) -> 18 | H17: =VLOOKUP(order_details__2[[#This Row],[OrderID]],orders[],20,FALSE) -> 1996 | I17: =VLOOKUP(order_details__2[[#This Row],[ProductID]],products[],2,FALSE) -> Chartreuse verte | J17: =VLOOKUP(order_details__2[[#This Row],[SupplierID]],suppliers[],2,FALSE) -> Aux joyeux ecclsiastiques | K17: =VLOOKUP(order_details__2[[#This Row],[OrderID]],orders[],14,FALSE) -> Brazil | L17: =VLOOKUP(order_details__2[[#This Row],[OrderID]],orders[],7,FALSE) -> 2 | M17: =VLOOKUP(order_details__2[[#This Row],[ShipVia ]],shippers[],2,FALSE) -> United Package | N17: =VLOOKUP(order_details__2[[#This Row],[OrderID]],orders[],2,FALSE) -> HANAR | O17: =VLOOKUP(order_details__2[[#This Row],[OrderID]],orders[],18,FALSE) -> Southern | P17: =VLOOKUP(order_details__2[[#This Row],[ProductID]],products[],4,FALSE) -> 1 | Q17: =VLOOKUP(order_details__2[[#This Row],[CategoryID]],categories[],2,FALSE) -> Beverages | R17: =VLOOKUP(order_details__2[[#This Row],[OrderID]],orders[],21,FALSE) -> 7
A18: 10253 | B18: 49 | C18: 16 | D18: 40 | E18: 0 | F18: =order_details__2[[#This Row],[UnitPrice]]*order_details__2[[#This Row],[Quantity]] -> 640 | G18: =VLOOKUP(order_details__2[[#This Row],[ProductID]],products[],3,FALSE) -> 23 | H18: =VLOOKUP(order_details__2[[#This Row],[OrderID]],orders[],20,FALSE) -> 1996 | I18: =VLOOKUP(order_details__2[[#This Row],[ProductID]],products[],2,FALSE) -> Maxilaku | J18: =VLOOKUP(order_details__2[[#This Row],[SupplierID]],suppliers[],2,FALSE) -> Karkki Oy | K18: =VLOOKUP(order_details__2[[#This Row],[OrderID]],orders[],14,FALSE) -> Brazil | L18: =VLOOKUP(order_details__2[[#This Row],[OrderID]],orders[],7,FALSE) -> 2 | M18: =VLOOKUP(order_details__2[[#This Row],[ShipVia ]],shippers[],2,FALSE) -> United Package | N18: =VLOOKUP(order_details__2[[#This Row],[OrderID]],orders[],2,FALSE) -> HANAR | O18: =VLOOKUP(order_details__2[[#This Row],[OrderID]],orders[],18,FALSE) -> Southern | P18: =VLOOKUP(order_details__2[[#This Row],[ProductID]],products[],4,FALSE) -> 3 | Q18: =VLOOKUP(order_details__2[[#This Row],[CategoryID]],categories[],2,FALSE) -> Confections | R18: =VLOOKUP(order_details__2[[#This Row],[OrderID]],orders[],21,FALSE) -> 7
A19: 10254 | B19: 24 | C19: 3.6 | D19: 15 | E19: 0 | F19: =order_details__2[[#This Row],[UnitPrice]]*order_details__2[[#This Row],[Quantity]] -> 54 | G19: =VLOOKUP(order_details__2[[#This Row],[ProductID]],products[],3,FALSE) -> 10 | H19: =VLOOKUP(order_details__2[[#This Row],[OrderID]],orders[],20,FALSE) -> 1996 | I19: =VLOOKUP(order_details__2[[#This Row],[ProductID]],products[],2,FALSE) -> Guaran Fantstica | J19: =VLOOKUP(order_details__2[[#This Row],[SupplierID]],suppliers[],2,FALSE) -> Refrescos Americanas LTDA | K19: =VLOOKUP(order_details__2[[#This Row],[OrderID]],orders[],14,FALSE) -> Switzerland | L19: =VLOOKUP(order_details__2[[#This Row],[OrderID]],orders[],7,FALSE) -> 2 | M19: =VLOOKUP(order_details__2[[#This Row],[ShipVia ]],shippers[],2,FALSE) -> United Package | N19: =VLOOKUP(order_details__2[[#This Row],[OrderID]],orders[],2,FALSE) -> CHOPS | O19: =VLOOKUP(order_details__2[[#This Row],[OrderID]],orders[],18,FALSE) -> Eastern | P19: =VLOOKUP(order_details__2[[#This Row],[ProductID]],products[],4,FALSE) -> 1 | Q19: =VLOOKUP(order_details__2[[#This Row],[CategoryID]],categories[],2,FALSE) -> Beverages | R19: =VLOOKUP(order_details__2[[#This Row],[OrderID]],orders[],21,FALSE) -> 7
A20: 10254 | B20: 55 | C20: 19.2 | D20: 21 | E20: 0 | F20: =order_details__2[[#This Row],[UnitPrice]]*order_details__2[[#This Row],[Quantity]] -> 403.2 | G20: =VLOOKUP(order_details__2[[#This Row],[ProductID]],products[],3,FALSE) -> 25 | H20: =VLOOKUP(order_details__2[[#This Row],[OrderID]],orders[],20,FALSE) -> 1996 | I20: =VLOOKUP(order_details__2[[#This Row],[ProductID]],products[],2,FALSE) -> Pt chinois | J20: =VLOOKUP(order_details__2[[#This Row],[SupplierID]],suppliers[],2,FALSE) -> Ma Maison | K20: =VLOOKUP(order_details__2[[#This Row],[OrderID]],orders[],14,FALSE) -> Switzerland | L20: =VLOOKUP(order_details__2[[#This Row],[OrderID]],orders[],7,FALSE) -> 2 | M20: =VLOOKUP(order_details__2[[#This Row],[ShipVia ]],shippers[],2,FALSE) -> United Package | N20: =VLOOKUP(order_details__2[[#This Row],[OrderID]],orders[],2,FALSE) -> CHOPS | O20: =VLOOKUP(order_details__2[[#This Row],[OrderID]],orders[],18,FALSE) -> Eastern | P20: =VLOOKUP(order_details__2[[#This Row],[ProductID]],products[],4,FALSE) -> 6 | Q20: =VLOOKUP(order_details__2[[#This Row],[CategoryID]],categories[],2,FALSE) -> Meat/Poultry | R20: =VLOOKUP(order_details__2[[#This Row],[OrderID]],orders[],21,FALSE) -> 7
A21: 10254 | B21: 74 | C21: 8 | D21: 21 | E21: 0 | F21: =order_details__2[[#This Row],[UnitPrice]]*order_details__2[[#This Row],[Quantity]] -> 168 | G21: =VLOOKUP(order_details__2[[#This Row],[ProductID]],products[],3,FALSE) -> 4 | H21: =VLOOKUP(order_details__2[[#This Row],[OrderID]],orders[],20,FALSE) -> 1996 | I21: =VLOOKUP(order_details__2[[#This Row],[ProductID]],products[],2,FALSE) -> Longlife Tofu | J21: =VLOOKUP(order_details__2[[#This Row],[SupplierID]],suppliers[],2,FALSE) -> Tokyo Traders | K21: =VLOOKUP(order_details__2[[#This Row],[OrderID]],orders[],14,FALSE) -> Switzerland | L21: =VLOOKUP(order_details__2[[#This Row],[OrderID]],orders[],7,FALSE) -> 2 | M21: =VLOOKUP(order_details__2[[#This Row],[ShipVia ]],shippers[],2,FALSE) -> United Package | N21: =VLOOKUP(order_details__2[[#This Row],[OrderID]],orders[],2,FALSE) -> CHOPS | O21: =VLOOKUP(order_details__2[[#This Row],[OrderID]],orders[],18,FALSE) -> Eastern | P21: =VLOOKUP(order_details__2[[#This Row],[ProductID]],products[],4,FALSE) -> 7 | Q21: =VLOOKUP(order_details__2[[#This Row],[CategoryID]],categories[],2,FALSE) -> Produce | R21: =VLOOKUP(order_details__2[[#This Row],[OrderID]],orders[],21,FALSE) -> 7
A22: 10255 | B22: 2 | C22: 15.2 | D22: 20 | E22: 0 | F22: =order_details__2[[#This Row],[UnitPrice]]*order_details__2[[#This Row],[Quantity]] -> 304 | G22: =VLOOKUP(order_details__2[[#This Row],[ProductID]],products[],3,FALSE) -> 1 | H22: =VLOOKUP(order_details__2[[#This Row],[OrderID]],orders[],20,FALSE) -> 1996 | I22: =VLOOKUP(order_details__2[[#This Row],[ProductID]],products[],2,FALSE) -> Chang | J22: =VLOOKUP(order_details__2[[#This Row],[SupplierID]],suppliers[],2,FALSE) -> Exotic Liquids | K22: =VLOOKUP(order_details__2[[#This Row],[OrderID]],orders[],14,FALSE) -> Switzerland | L22: =VLOOKUP(order_details__2[[#This Row],[OrderID]],orders[],7,FALSE) -> 3 | M22: =VLOOKUP(order_details__2[[#This Row],[ShipVia ]],shippers[],2,FALSE) -> Federal Shipping | N22: =VLOOKUP(order_details__2[[#This Row],[OrderID]],orders[],2,FALSE) -> RICSU | O22: =VLOOKUP(order_details__2[[#This Row],[OrderID]],orders[],18,FALSE) -> Northern | P22: =VLOOKUP(order_details__2[[#This Row],[ProductID]],products[],4,FALSE) -> 1 | Q22: =VLOOKUP(order_details__2[[#This Row],[CategoryID]],categories[],2,FALSE) -> Beverages | R22: =VLOOKUP(order_details__2[[#This Row],[OrderID]],orders[],21,FALSE) -> 7
A23: 10255 | B23: 16 | C23: 13.9 | D23: 35 | E23: 0 | F23: =order_details__2[[#This Row],[UnitPrice]]*order_details__2[[#This Row],[Quantity]] -> 486.5 | G23: =VLOOKUP(order_details__2[[#This Row],[ProductID]],products[],3,FALSE) -> 7 | H23: =VLOOKUP(order_details__2[[#This Row],[OrderID]],orders[],20,FALSE) -> 1996 | I23: =VLOOKUP(order_details__2[[#This Row],[ProductID]],products[],2,FALSE) -> Pavlova | J23: =VLOOKUP(order_details__2[[#This Row],[SupplierID]],suppliers[],2,FALSE) -> Pavlova, Ltd. | K23: =VLOOKUP(order_details__2[[#This Row],[OrderID]],orders[],14,FALSE) -> Switzerland | L23: =VLOOKUP(order_details__2[[#This Row],[OrderID]],orders[],7,FALSE) -> 3 | M23: =VLOOKUP(order_details__2[[#This Row],[ShipVia ]],shippers[],2,FALSE) -> Federal Shipping | N23: =VLOOKUP(order_details__2[[#This Row],[OrderID]],orders[],2,FALSE) -> RICSU | O23: =VLOOKUP(order_details__2[[#This Row],[OrderID]],orders[],18,FALSE) -> Northern | P23: =VLOOKUP(order_details__2[[#This Row],[ProductID]],products[],4,FALSE) -> 3 | Q23: =VLOOKUP(order_details__2[[#This Row],[CategoryID]],categories[],2,FALSE) -> Confections | R23: =VLOOKUP(order_details__2[[#This Row],[OrderID]],orders[],21,FALSE) -> 7
A24: 10255 | B24: 36 | C24: 15.2 | D24: 25 | E24: 0 | F24: =order_details__2[[#This Row],[UnitPrice]]*order_details__2[[#This Row],[Quantity]] -> 380 | G24: =VLOOKUP(order_details__2[[#This Row],[ProductID]],products[],3,FALSE) -> 17 | H24: =VLOOKUP(order_details__2[[#This Row],[OrderID]],orders[],20,FALSE) -> 1996 | I24: =VLOOKUP(order_details__2[[#This Row],[ProductID]],products[],2,FALSE) -> Inlagd Sill | J24: =VLOOKUP(order_details__2[[#This Row],[SupplierID]],suppliers[],2,FALSE) -> Svensk Sjfda AB | K24: =VLOOKUP(order_details__2[[#This Row],[OrderID]],orders[],14,FALSE) -> Switzerland | L24: =VLOOKUP(order_details__2[[#This Row],[OrderID]],orders[],7,FALSE) -> 3 | M24: =VLOOKUP(order_details__2[[#This Row],[ShipVia ]],shippers[],2,FALSE) -> Federal Shipping | N24: =VLOOKUP(order_details__2[[#This Row],[OrderID]],orders[],2,FALSE) -> RICSU | O24: =VLOOKUP(order_details__2[[#This Row],[OrderID]],orders[],18,FALSE) -> Northern | P24: =VLOOKUP(order_details__2[[#This Row],[ProductID]],products[],4,FALSE) -> 8 | Q24: =VLOOKUP(order_details__2[[#This Row],[CategoryID]],categories[],2,FALSE) -> Seafood | R24: =VLOOKUP(order_details__2[[#This Row],[OrderID]],orders[],21,FALSE) -> 7
... A2156: 11077 | B2156: 77 | C2156: 13 | D2156: 2 | E2156: 0 | F2156: =order_details__2[[#This Row],[UnitPrice]]*order_details__2[[#This Row],[Quantity]] -> 26 | G2156: =VLOOKUP(order_details__2[[#This Row],[ProductID]],products[],3,FALSE) -> 12 | H2156: =VLOOKUP(order_details__2[[#This Row],[OrderID]],orders[],20,FALSE) -> 1998 | I2156: =VLOOKUP(order_details__2[[#This Row],[ProductID]],products[],2,FALSE) -> Original Frankfurter grne Soe | J2156: =VLOOKUP(order_details__2[[#This Row],[SupplierID]],suppliers[],2,FALSE) -> Plutzer Lebensmittelgromrkte AG | K2156: =VLOOKUP(order_details__2[[#This Row],[OrderID]],orders[],14,FALSE) -> USA | L2156: =VLOOKUP(order_details__2[[#This Row],[OrderID]],orders[],7,FALSE) -> 2 | M2156: =VLOOKUP(order_details__2[[#This Row],[ShipVia ]],shippers[],2,FALSE) -> United Package | N2156: =VLOOKUP(order_details__2[[#This Row],[OrderID]],orders[],2,FALSE) -> RATTC | O2156: =VLOOKUP(order_details__2[[#This Row],[OrderID]],orders[],18,FALSE) -> Eastern | P2156: =VLOOKUP(order_details__2[[#This Row],[ProductID]],products[],4,FALSE) -> 2 | Q2156: =VLOOKUP(order_details__2[[#This Row],[CategoryID]],categories[],2,FALSE) -> Condiments | R2156: =VLOOKUP(order_details__2[[#This Row],[OrderID]],orders[],21,FALSE) -> 5

Sheet order_detail_pivot
A3: Row Labels | B3: Sum of Line Sale
A4: Rssle Sauerkraut | B4: 26865.6
A5: Carnarvon Tigers | B5: 31987.5
A6: Alice Mutton | B6: 35482.2
A7: Manjimup Dried Apples | B7: 44742.6
A8: Gnocchi di nonna Alice | B8: 45121.2
A9: Tarte au sucre | B9: 49827.9
A10: Camembert Pierrot | B10: 50286
A11: Raclette Courdavault | B11: 76296
A12: Thringer Rostbratwurst | B12: 87736.4
A13: Cte de Blaye | B13: 149984.2
A14: Grand Total | B14: 598329.6
A20: Row Labels | B20: Sum of Quantity
A21: Flotemysost | B21: 1057
A22: Chang | B22: 1057
A23: Tarte au sucre | B23: 1083
A24: Boston Crab Meat | B24: 1103
A25: Guaran Fantstica | B25: 1125
A26: Rhnbru Klosterbier | B26: 1155
A27: Pavlova | B27: 1158
A28: Gnocchi di nonna Alice | B28: 1263
A29: Gorgonzola Telino | B29: 1397
A30: Raclette Courdavault | B30: 1496
A31: Camembert Pierrot | B31: 1577
A32: Grand Total | B32: 13471
A37: Row Labels | B37: Sum of Line Sale
A38: Norske Meierier | B38: 46897.2
A39: Specialty Biscuits, Ltd. | B39: 48793.8
A40: Formaggi Fortini s.r.l. | B40: 51082.5
A41: Pasta Buttini s.r.l. | B41: 52929
A42: Forts d'rables | B42: 66266.7
A43: G'day, Mate | B43: 69636.6
A44: Pavlova, Ltd. | B44: 115386.05
A45: Gai pturage | B45: 126582
A46: Plutzer Lebensmittelgromrkte AG | B46: 155946.55
A47: Aux joyeux ecclsiastiques | B47: 163135
A48: Grand Total | B48: 896655.4
A54: Row Labels | B54: Sum of Quantity
A55: Flotemysost | B55: 1057
A56: Chang | B56: 1057
A57: Tarte au sucre | B57: 1083
A58: Boston Crab Meat | B58: 1103
A59: Guaran Fantstica | B59: 1125
A60: Rhnbru Klosterbier | B60: 1155
A61: Pavlova | B61: 1158
A62: Gnocchi di nonna Alice | B62: 1263
A63: Gorgonzola Telino | B63: 1397
A64: Raclette Courdavault | B64: 1496
A65: Camembert Pierrot | B65: 1577
A66: Grand Total | B66: 13471
A71: Row Labels | B71: Sum of Line Sale
A72: 1996 | B72: 226298.5
A73: 1997 | B73: 658388.75
A74: 1998 | B74: 469771.34
A75: Grand Total | B75: 1354458.6
B76: =GETPIVOTDATA("Line Sale",$A$71) -> 1354458.6
A80: Row Labels | B80: Sum of Line Sale
A81: Grains/Cereals | B81: 100726.8
A82: Produce | B82: 105268.6
A83: Condiments | B83: 113694.75
A84: Seafood | B84: 141623.09
A85: Confections | B85: 177099.1
A86: Meat/Poultry | B86: 178188.8
A87: Dairy Products | B87: 251330.5
A88: Beverages | B88: 286526.95
A89: Grand Total | B89: 1354458.6
A97: Row Labels | B97: Sum of Line Sale
A98: Argentina | B98: 8119.1 | D98: =A98 -> Argentina | E98: =GETPIVOTDATA("Line Sale",$A$97,"ShipCountry","Argentina") -> 8119.1
A99: Austria | B99: 139496.63 | D99: =A99 -> Austria | E99: =GETPIVOTDATA("Line Sale",$A$97,"ShipCountry","Austria") -> 139496.63
A100: Belgium | B100: 35134.98 | D100: =A100 -> Belgium | E100: =GETPIVOTDATA("Line Sale",$A$97,"ShipCountry","Belgium") -> 35134.98
A101: Brazil | B101: 114968.48 | D101: =A101 -> Brazil | E101: =GETPIVOTDATA("Line Sale",$A$97,"ShipCountry","Brazil") -> 114968.48
A102: Canada | B102: 55334.1 | D102: =A102 -> Canada | E102: =GETPIVOTDATA("Line Sale",$A$97,"ShipCountry","Canada") -> 55334.1
A103: Denmark | B103: 34782.25 | D103: =A103 -> Denmark | E103: =GETPIVOTDATA("Line Sale",$A$97,"ShipCountry","Denmark") -> 34782.25
A104: Finland | B104: 19778.45 | D104: =A104 -> Finland | E104: =GETPIVOTDATA("Line Sale",$A$97,"ShipCountry","Finland") -> 19778.45
A105: France | B105: 85498.76 | D105: =A105 -> France | E105: =GETPIVOTDATA("Line Sale",$A$97,"ShipCountry","France") -> 85498.76
A106: Germany | B106: 244640.63 | D106: =A106 -> Germany | E106: =GETPIVOTDATA("Line Sale",$A$97,"ShipCountry","Germany") -> 244640.63
A107: Ireland | B107: 57317.39 | D107: =A107 -> Ireland | E107: =GETPIVOTDATA("Line Sale",$A$97,"ShipCountry","Ireland") -> 57317.39
A108: Italy | B108: 16705.15 | D108: =A108 -> Italy | E108: =GETPIVOTDATA("Line Sale",$A$97,"ShipCountry","Italy") -> 16705.15
A109: Mexico | B109: 24073.45 | D109: =A109 -> Mexico | E109: =GETPIVOTDATA("Line Sale",$A$97,"ShipCountry","Mexico") -> 24073.45
A110: Norway | B110: 5735.15 | D110: =A110 -> Norway | E110: =GETPIVOTDATA("Line Sale",$A$97,"ShipCountry","Norway") -> 5735.15
A111: Poland | B111: 3531.95 | D111: =A111 -> Poland | E111: =GETPIVOTDATA("Line Sale",$A$97,"ShipCountry","Poland") -> 3531.95
A112: Portugal | B112: 12468.65 | D112: =A112 -> Portugal | E112: =GETPIVOTDATA("Line Sale",$A$97,"ShipCountry","Portugal") -> 12468.65
A113: Spain | B113: 19431.89 | D113: =A113 -> Spain | E113: =GETPIVOTDATA("Line Sale",$A$97,"ShipCountry","Spain") -> 19431.89
A114: Sweden | B114: 59523.7 | D114: =A114 -> Sweden | E114: =GETPIVOTDATA("Line Sale",$A$97,"ShipCountry","Sweden") -> 59523.7
A115: Switzerland | B115: 32919.5 | D115: =A115 -> Switzerland | E115: =GETPIVOTDATA("Line Sale",$A$97,"ShipCountry","Switzerland") -> 32919.5
A116: UK | B116: 60616.51 | D116: =A116 -> UK | E116: =GETPIVOTDATA("Line Sale",$A$97,"ShipCountry","UK") -> 60616.51
A117: USA | B117: 263566.98 | D117: =A117 -> USA | E117: =GETPIVOTDATA("Line Sale",$A$97,"ShipCountry","USA") -> 263566.98
A118: Venezuela | B118: 60814.89 | D118: =A118 -> Venezuela | E118: =GETPIVOTDATA("Line Sale",$A$97,"ShipCountry","Venezuela") -> 60814.89
A119: Grand Total | B119: 1354458.6
A123: Row Labels | B123: Sum of Line Sale
A124: Eastern | B124: 0.52098172
A125: Northern | B125: 0.15966899
A126: Southern | B126: 0.15729628
A127: Westerns | B127: 0.16205301
A128: Grand Total | B128: 1
A139: Count of OrderID | B139: Sum of Quantity
A140: 2155 | B140: 51317
A141: =GETPIVOTDATA("OrderID",$A$139) -> 2155 | B141: =GETPIVOTDATA("Sum of Quantity",$A$139) -> 51317
A144: Row Labels | B144: Sum of Line Sale
A145: 1 | B145: 167547.52
...

Sheet order_details
A1: OrderID
A2: 10248
A3: 10248 | C3: OrderID | D3: OrderSum | E3: ShipID | F3: OrderQuantity
A4: 10248 | C4: 10248 | D4: =SUMIF(order_details__2[OrderID],order_details!C4,order_details__2[Line Sale]) -> 440 | E4: =VLOOKUP(Table15[[#This Row],[OrderID]],orders[],7,FALSE) -> 3 | F4: =SUMIF(order_details__2[OrderID],Table15[[#This Row],[OrderID]],order_details__2[Quantity]) -> 27
A5: 10249 | C5: 10249 | D5: =SUMIF(order_details__2[OrderID],order_details!C5,order_details__2[Line Sale]) -> 1863.4 | E5: =VLOOKUP(Table15[[#This Row],[OrderID]],orders[],7,FALSE) -> 1 | F5: =SUMIF(order_details__2[OrderID],Table15[[#This Row],[OrderID]],order_details__2[Quantity]) -> 49
A6: 10249 | C6: 10250 | D6: =SUMIF(order_details__2[OrderID],order_details!C6,order_details__2[Line Sale]) -> 1813 | E6: =VLOOKUP(Table15[[#This Row],[OrderID]],orders[],7,FALSE) -> 2 | F6: =SUMIF(order_details__2[OrderID],Table15[[#This Row],[OrderID]],order_details__2[Quantity]) -> 60
A7: 10250 | C7: 10251 | D7: =SUMIF(order_details__2[OrderID],order_details!C7,order_details__2[Line Sale]) -> 670.8 | E7: =VLOOKUP(Table15[[#This Row],[OrderID]],orders[],7,FALSE) -> 1 | F7: =SUMIF(order_details__2[OrderID],Table15[[#This Row],[OrderID]],order_details__2[Quantity]) -> 41
A8: 10250 | C8: 10252 | D8: =SUMIF(order_details__2[OrderID],order_details!C8,order_details__2[Line Sale]) -> 3730 | E8: =VLOOKUP(Table15[[#This Row],[OrderID]],orders[],7,FALSE) -> 2 | F8: =SUMIF(order_details__2[OrderID],Table15[[#This Row],[OrderID]],order_details__2[Quantity]) -> 105
A9: 10250 | C9: 10253 | D9: =SUMIF(order_details__2[OrderID],order_details!C9,order_details__2[Line Sale]) -> 1444.8 | E9: =VLOOKUP(Table15[[#This Row],[OrderID]],orders[],7,FALSE) -> 2 | F9: =SUMIF(order_details__2[OrderID],Table15[[#This Row],[OrderID]],order_details__2[Quantity]) -> 102
A10: 10251 | C10: 10254 | D10: =SUMIF(order_details__2[OrderID],order_details!C10,order_details__2[Line Sale]) -> 625.2 | E10: =VLOOKUP(Table15[[#This Row],[OrderID]],orders[],7,FALSE) -> 2 | F10: =SUMIF(order_details__2[OrderID],Table15[[#This Row],[OrderID]],order_details__2[Quantity]) -> 57
A11: 10251 | C11: 10255 | D11: =SUMIF(order_details__2[OrderID],order_details!C11,order_details__2[Line Sale]) -> 2490.5 | E11: =VLOOKUP(Table15[[#This Row],[OrderID]],orders[],7,FALSE) -> 3 | F11: =SUMIF(order_details__2[OrderID],Table15[[#This Row],[OrderID]],order_details__2[Quantity]) -> 110
A12: 10251 | C12: 10256 | D12: =SUMIF(order_details__2[OrderID],order_details!C12,order_details__2[Line Sale]) -> 517.8 | E12: =VLOOKUP(Table15[[#This Row],[OrderID]],orders[],7,FALSE) -> 2 | F12: =SUMIF(order_details__2[OrderID],Table15[[#This Row],[OrderID]],order_details__2[Quantity]) -> 27
A13: 10252 | C13: 10257 | D13: =SUMIF(order_details__2[OrderID],order_details!C13,order_details__2[Line Sale]) -> 1119.9 | E13: =VLOOKUP(Table15[[#This Row],[OrderID]],orders[],7,FALSE) -> 3 | F13: =SUMIF(order_details__2[OrderID],Table15[[#This Row],[OrderID]],order_details__2[Quantity]) -> 46
A14: 10252 | C14: 10258 | D14: =SUMIF(order_details__2[OrderID],order_details!C14,order_details__2[Line Sale]) -> 2018.6 | E14: =VLOOKUP(Table15[[#This Row],[OrderID]],orders[],7,FALSE) -> 1 | F14: =SUMIF(order_details__2[OrderID],Table15[[#This Row],[OrderID]],order_details__2[Quantity]) -> 121
A15: 10252 | C15: 10259 | D15: =SUMIF(order_details__2[OrderID],order_details!C15,order_details__2[Line Sale]) -> 100.8 | E15: =VLOOKUP(Table15[[#This Row],[OrderID]],orders[],7,FALSE) -> 3 | F15: =SUMIF(order_details__2[OrderID],Table15[[#This Row],[OrderID]],order_details__2[Quantity]) -> 11
... A833: 10558 | C833: 11077 | D833: =SUMIF(order_details__2[OrderID],order_details!C833,order_details__2[Line Sale]) -> 1374.6 | E833: =VLOOKUP(Table15[[#This Row],[OrderID]],orders[],7,FALSE) -> 2 | F833: =SUMIF(order_details__2[OrderID],Table15[[#This Row],[OrderID]],order_details__2[Quantity]) -> 72
A834: 10558
A835: 10558
A836: 10558
A837: 10558
A838: 10559
A839: 10559
A840: 10560
A841: 10560
A842: 10561
A843: 10561
A844: 10562
A845: 10562
... A2156: 11077

Sheet employees
A1: EmployeeID | B1: LastName | C1: FirstName | D1: Title | E1: TitleOfCourtesy | F1: BirthDate | G1: HireDate | H1: Address | I1: City | J1: Region | K1: Country | L1: HomePhone | M1: Salary | N1: Column1
A2: 1 | B2: Davolio | C2: Nancy | D2: Sales Representative | E2: Ms. | F2: 17875 | G2: 33725 | H2: 507 - 20th Ave. E.Apt. 2A | I2: Seattle | J2: WA | K2: USA | L2: (206) 555-9857 | M2: 2954.55
A3: 2 | B3: Fuller | C3: Andrew | D3: Vice President, Sales | E3: Dr. | F3: 19043 | G3: 33830 | H3: 908 W. Capital Way | I3: Tacoma | J3: WA | K3: USA | L3: (206) 555-9482 | M3: 2254.49
A4: 3 | B4: Leverling | C4: Janet | D4: Sales Representative | E4: Ms. | F4: 23253 | G4: 33695 | H4: 722 Moss Bay Blvd. | I4: Kirkland | J4: WA | K4: USA | L4: (206) 555-3412 | M4: 3119.15
A5: 4 | B5: Peacock | C5: Margaret | D5: Sales Representative | E5: Mrs. | F5: 13777 | G5: 34092 | H5: 4110 Old Redmond Rd. | I5: Redmond | J5: WA | K5: USA | L5: (206) 555-8122 | M5: 1861.08
A6: 5 | B6: Buchanan | C6: Steven | D6: Sales Manager | E6: Mr. | F6: 20152 | G6: 34259 | H6: 14 Garrett Hill | I6: London | J6: NULL | K6: UK | L6: (71) 555-4848 | M6: 1744.21
A7: 6 | B7: Suyama | C7: Michael | D7: Sales Representative | E7: Mr. | F7: 23194 | G7: 34259 | H7: Coventry House Miner Rd. | I7: London | J7: NULL | K7: UK | L7: (71) 555-7773 | M7: 2004.07
A8: 7 | B8: King | C8: Robert | D8: Sales Representative | E8: Mr. | F8: 22065 | G8: 34336 | H8: Edgeham Hollow Winchester Way | I8: London | J8: NULL | K8: UK | L8: (71) 555-5598 | M8: 1991.55
A9: 8 | B9: Callahan | C9: Laura | D9: Inside Sales Coordinator | E9: Ms. | F9: 21194 | G9: 34398 | H9: 4726 - 11th Ave. N.E. | I9: Seattle | J9: WA | K9: USA | L9: (206) 555-1189 | M9: 2100.5
A10: 9 | B10: Dodsworth | C10: Anne | D10: Sales Representative | E10: Ms. | F10: 24134 | G10: 34653 | H10: 7 Houndstooth Rd. | I10: London | J10: NULL | K10: UK | L10: (71) 555-4444 | M10: 2333.33

Sheet employee_territory
A1: EmployeeID | B1: TerritoryID
A2: 1 | B2: 6897
A3: 1 | B3: 19713
A4: 2 | B4: 1581
A5: 2 | B5: 1730
A6: 2 | B6: 1833
A7: 2 | B7: 2116
A8: 2 | B8: 2139
A9: 2 | B9: 2184
A10: 2 | B10: 40222
A11: 3 | B11: 30346
A12: 3 | B12: 31406
A13: 3 | B13: 32859
... A50: 9 | B50: 55439

Sheet customers (2)
A1: CustomerID | B1: CompanyName | C1: ContactName | D1: ContactTitle | E1: Address | F1: City | G1: Region | H1: PostalCode | I1: Country | J1: Phone | K1: Fax | L1: CustomerSale
A2: ALFKI | B2: Alfreds Futterkiste | C2: Maria Anders | D2: Sales Representative | E2: Obere Str. 57 | F2: Berlin | G2: NULL | H2: 12209 | I2: Germany | J2: 030-0074321 | K2: 030-0076545 | L2: =SUMIF(orders[CustomerID],customers__2[[#This Row],[CustomerID]],orders[[Order Sale ]]) -> 4596.2
A3: ANATR | B3: Ana Trujillo Emparedados y helados | C3: Ana Trujillo | D3: Owner | E3: Avda. de la Constitucin 2222 | F3: Mxico D.F. | G3: NULL | H3: 05021 | I3: Mexico | J3: (5) 555-4729 | K3: (5) 555-3745 | L3: =SUMIF(orders[CustomerID],customers__2[[#This Row],[CustomerID]],orders[[Order Sale ]]) -> 1402.95
A4: ANTON | B4: Antonio Moreno Taquera | C4: Antonio Moreno | D4: Owner | E4: Mataderos 2312 | F4: Mxico D.F. | G4: NULL | H4: 05023 | I4: Mexico | J4: (5) 555-3932 | K4: NULL | L4: =SUMIF(orders[CustomerID],customers__2[[#This Row],[CustomerID]],orders[[Order Sale ]]) -> 7515.35
A5: AROUT | B5: Around the Horn | C5: Thomas Hardy | D5: Sales Representative | E5: 120 Hanover Sq. | F5: London | G5: NULL | H5: WA1 1DP | I5: UK | J5: (171) 555-7788 | K5: (171) 555-6750 | L5: =SUMIF(orders[CustomerID],customers__2[[#This Row],[CustomerID]],orders[[Order Sale ]]) -> 13806.5
A6: BERGS | B6: Berglunds snabbkp | C6: Christina Berglund | D6: Order Administrator | E6: Berguvsvgen 8 | F6: Lule | G6: NULL | H6: S-958 22 | I6: Sweden | J6: 0921-12 34 65 | K6: 0921-12 34 67 | L6: =SUMIF(orders[CustomerID],customers__2[[#This Row],[CustomerID]],orders[[Order Sale ]]) -> 26968.15
A7: BLAUS | B7: Blauer See Delikatessen | C7: Hanna Moos | D7: Sales Representative | E7: Forsterstr. 57 | F7: Mannheim | G7: NULL | H7: 68306 | I7: Germany | J7: 0621-08460 | K7: 0621-08924 | L7: =SUMIF(orders[CustomerID],customers__2[[#This Row],[CustomerID]],orders[[Order Sale ]]) -> 3239.8
A8: BLONP | B8: Blondesddsl pre et fils | C8: Frdrique Citeaux | D8: Marketing Manager | E8: 24, place Klber | F8: Strasbourg | G8: NULL | H8: 67000 | I8: France | J8: 88.60.15.31 | K8: 88.60.15.32 | L8: =SUMIF(orders[CustomerID],customers__2[[#This Row],[CustomerID]],orders[[Order Sale ]]) -> 19088
A9: BOLID | B9: Blido Comidas preparadas | C9: Martn Sommer | D9: Owner | E9: C/ Araquil, 67 | F9: Madrid | G9: NULL | H9: 28023 | I9: Spain | J9: (91) 555 22 82 | K9: (91) 555 91 99 | L9: =SUMIF(orders[CustomerID],customers__2[[#This Row],[CustomerID]],orders[[Order Sale ]]) -> 5297.8
A10: BONAP | B10: Bon app' | C10: Laurence Lebihan | D10: Owner | E10: 12, rue des Bouchers | F10: Marseille | G10: NULL | H10: 13008 | I10: France | J10: 91.24.45.40 | K10: 91.24.45.41 | L10: =SUMIF(orders[CustomerID],customers__2[[#This Row],[CustomerID]],orders[[Order Sale ]]) -> 23850.95
A11: BOTTM | B11: Bottom-Dollar Markets | C11: Elizabeth Lincoln | D11: Accounting Manager | E11: 23 Tsawassen Blvd. | F11: Tsawassen | G11: BC | H11: T2F 8M4 | I11: Canada | J11: (604) 555-4729 | K11: (604) 555-3745 | L11: =SUMIF(orders[CustomerID],customers__2[[#This Row],[CustomerID]],orders[[Order Sale ]]) -> 22607.7
A12: BSBEV | B12: B's Beverages | C12: Victoria Ashworth | D12: Sales Representative | E12: Fauntleroy Circus | F12: London | G12: NULL | H12: EC2 5NT | I12: UK | J12: (171) 555-1212 | K12: NULL | L12: =SUMIF(orders[CustomerID],customers__2[[#This Row],[CustomerID]],orders[[Order Sale ]]) -> 6089.9
A13: CACTU | B13: Cactus Comidas para llevar | C13: Patricio Simpson | D13: Sales Agent | E13: Cerrito 333 | F13: Buenos Aires | G13: NULL | H13: 1010 | I13: Argentina | J13: (1) 135-5555 | K13: (1) 135-4892 | L13: =SUMIF(orders[CustomerID],customers__2[[#This Row],[CustomerID]],orders[[Order Sale ]]) -> 1814.8
... A94: WOLZA | B94: Wolski Zajazd | C94: Zbyszek Piestrzeniewicz | D94: Owner | E94: ul. Filtrowa 68 | F94: Warszawa | G94: NULL | H94: 01-012 | I94: Poland | J94: (26) 642-7012 | K94: (26) 642-7012 | L94: =SUMIF(orders[CustomerID],customers__2[[#This Row],[CustomerID]],orders[[Order Sale ]]) -> 3531.95

Sheet categories
A1: CategoryID | B1: CategoryName | C1: Description | D1: CategorySale
A2: 1 | B2: Beverages | C2: Soft drinks, coffees, teas, beers, and ales | D2: =SUMIF(products[CategoryID],categories[[#This Row],[CategoryID]],products[[Product Sale ]]) -> 286526.95
A3: 2 | B3: Condiments | C3: Sweet and savory sauces, relishes, spreads, and seasonings | D3: =SUMIF(products[CategoryID],categories[[#This Row],[CategoryID]],products[[Product Sale ]]) -> 113694.75
A4: 3 | B4: Confections | C4: Desserts, candies, and sweet breads | D4: =SUMIF(products[CategoryID],categories[[#This Row],[CategoryID]],products[[Product Sale ]]) -> 177099.1
A5: 4 | B5: Dairy Products | C5: Cheeses | D5: =SUMIF(products[CategoryID],categories[[#This Row],[CategoryID]],products[[Product Sale ]]) -> 251330.5
A6: 5 | B6: Grains/Cereals | C6: Breads, crackers, pasta, and cereal | D6: =SUMIF(products[CategoryID],categories[[#This Row],[CategoryID]],products[[Product Sale ]]) -> 100726.8
A7: 6 | B7: Meat/Poultry | C7: Prepared meats | D7: =SUMIF(products[CategoryID],categories[[#This Row],[CategoryID]],products[[Product Sale ]]) -> 178188.8
A8: 7 | B8: Produce | C8: Dried fruit and bean curd | D8: =SUMIF(products[CategoryID],categories[[#This Row],[CategoryID]],products[[Product Sale ]]) -> 105268.6
A9: 8 | B9: Seafood | C9: Seaweed and fish | D9: =SUMIF(products[CategoryID],categories[[#This Row],[CategoryID]],products[[Product Sale ]]) -> 141623.09
